[["ATL201104080", {"Team name": "Phillies", "Home": "5-1", "Road": "0-0", "ExtrInn": "0-0", "vsRHP": "3-1", "vsLHP": "2-0", "1-Run": "1-0", "vsEast": "2-1", "vsCntrl": "3-0", "vsWest": "0-0", "IL": "0-0", "last_10_game": [["0407", 1, "NYM", 1, "11-0", "5-1", 1, 2.0], ["0406", 1, "NYM", 1, "10-7", "4-1", 1, 1.0], ["0405", 1, "NYM", 0, "1-7", "3-1", 1, 0.0], ["0403", 1, "HOU", 1, "7-3", "3-0", 1, 1.0], ["0402", 1, "HOU", 1, "9-4", "2-0", 1, 1.0], ["0401", 1, "HOU", 1, "5-4", "1-0", 1, 0.0], [null, null, null, null, null, null, null, null], [null, null, null, null, null, null, null, null], [null, null, null, null, null, null, null, null], [null, null, null, null, null, null, null, null]]}, {"Team name": "Braves", "Home": "0-0", "Road": "3-4", "ExtrInn": "0-0", "vsRHP": "2-3", "vsLHP": "1-1", "1-Run": "1-2", "vsEast": "2-1", "vsCntrl": "1-3", "vsWest": "0-0", "IL": "0-0", "last_10_game": [["0407", 0, "MIL", 0, "2-4", "3-4", 4, 2.5], ["0406", 0, "MIL", 0, "4-5", "3-3", 4, 1.5], ["0405", 0, "MIL", 0, "0-1", "3-2", 3, 0.5], ["0404", 0, "MIL", 1, "2-1", "3-1", 2, 0.5], ["0403", 0, "WSN", 1, "11-2", "2-1", 2, 1.0], ["0402", 0, "WSN", 0, "3-6", "1-1", 2, 1.0], ["0331", 0, "WSN", 1, "2-0", "1-0", 1, 0.5], [null, null, null, null, null, null, null, null], [null, null, null, null, null, null, null, null], [null, null, null, null, null, null, null, null]]}, [["20101003", "ATL", "PHI", 1, 8, 7], ["20101002", "PHI", "ATL", 0, 7, 0], ["20101001", "PHI", "ATL", 0, 11, 5], ["20100922", "PHI", "ATL", 1, 1, 0], ["20100921", "PHI", "ATL", 1, 5, 3], ["20100920", "PHI", "ATL", 1, 3, 1], ["20100707", "ATL", "PHI", 0, 7, 5], ["20100706", "ATL", "PHI", 0, 6, 3], ["20100705", "PHI", "ATL", 1, 3, 1], ["20100602", "ATL", "PHI", 1, 2, 1]]], ["ATL201104090", {"Team name": "Phillies", "Home": "5-1", "Road": "0-1", "ExtrInn": "0-0", "vsRHP": "3-2", "vsLHP": "2-0", "1-Run": "1-0", "vsEast": "2-2", "vsCntrl": "3-0", "vsWest": "0-0", "IL": "0-0", "last_10_game": [["0408", 0, "ATL", 0, "3-6", "5-2", 1, 1.0], ["0407", 1, "NYM", 1, "11-0", "5-1", 1, 2.0], ["0406", 1, "NYM", 1, "10-7", "4-1", 1, 1.0], ["0405", 1, "NYM", 0, "1-7", "3-1", 1, 0.0], ["0403", 1, "HOU", 1, "7-3", "3-0", 1, 1.0], ["0402", 1, "HOU", 1, "9-4", "2-0", 1, 1.0], ["0401", 1, "HOU", 1, "5-4", "1-0", 1, 0.0], [null, null, null, null, null, null, null, null], [null, null, null, null, null, null, null, null], [null, null, null, null, null, null, null, null]]}, {"Team name": "Braves", "Home": "1-0", "Road": "3-4", "ExtrInn": "0-0", "vsRHP": "2-3", "vsLHP": "2-1", "1-Run": "1-2", "vsEast": "3-1", "vsCntrl": "1-3", "vsWest": "0-0", "IL": "0-0", "last_10_game": [["0408", 1, "PHI", 1, "6-3", "4-4", 3, 1.5], ["0407", 0, "MIL", 0, "2-4", "3-4", 4, 2.5], ["0406", 0, "MIL", 0, "4-5", "3-3", 4, 1.5], ["0405", 0, "MIL", 0, "0-1", "3-2", 3, 0.5], ["0404", 0, "MIL", 1, "2-1", "3-1", 2, 0.5], ["0403", 0, "WSN", 1, "11-2", "2-1", 2, 1.0], ["0402", 0, "WSN", 0, "3-6", "1-1", 2, 1.0], ["0331", 0, "WSN", 1, "2-0", "1-0", 1, 0.5], [null, null, null, null, null, null, null, null], [null, null, null, null, null, null, null, null]]}, [["20110408", "ATL", "PHI", 1, 6, 3], ["20101003", "ATL", "PHI", 1, 8, 7], ["20101002", "PHI", "ATL", 0, 7, 0], ["20101001", "PHI", "ATL", 0, 11, 5], ["20100922", "PHI", "ATL", 1, 1, 0], ["20100921", "PHI", "ATL", 1, 5, 3], ["20100920", "PHI", "ATL", 1, 3, 1], ["20100707", "ATL", "PHI", 0, 7, 5], ["20100706", "ATL", "PHI", 0, 6, 3], ["20100705", "PHI", "ATL", 1, 3, 1]]], ["ATL201104100", {"Team name": "Phillies", "Home": "5-1", "Road": "1-1", "ExtrInn": "0-0", "vsRHP": "4-2", "vsLHP": "2-0", "1-Run": "1-0", "vsEast": "3-2", "vsCntrl": "3-0", "vsWest": "0-0", "IL": "0-0", "last_10_game": [["0409", 0, "ATL", 1, "10-2", "6-2", 1, 1.0], ["0408", 0, "ATL", 0, "3-6", "5-2", 1, 1.0], ["0407", 1, "NYM", 1, "11-0", "5-1", 1, 2.0], ["0406", 1, "NYM", 1, "10-7", "4-1", 1, 1.0], ["0405", 1, "NYM", 0, "1-7", "3-1", 1, 0.0], ["0403", 1, "HOU", 1, "7-3", "3-0", 1, 1.0], ["0402", 1, "HOU", 1, "9-4", "2-0", 1, 1.0], ["0401", 1, "HOU", 1, "5-4", "1-0", 1, 0.0], [null, null, null, null, null, null, null, null], [null, null, null, null, null, null, null, null]]}, {"Team name": "Braves", "Home": "1-1", "Road": "3-4", "ExtrInn": "0-0", "vsRHP": "2-4", "vsLHP": "2-1", "1-Run": "1-2", "vsEast": "3-2", "vsCntrl": "1-3", "vsWest": "0-0", "IL": "0-0", "last_10_game": [["0409", 1, "PHI", 0, "2-10", "4-5", 4, 2.5], ["0408", 1, "PHI", 1, "6-3", "4-4", 3, 1.5], ["0407", 0, "MIL", 0, "2-4", "3-4", 4, 2.5], ["0406", 0, "MIL", 0, "4-5", "3-3", 4, 1.5], ["0405", 0, "MIL", 0, "0-1", "3-2", 3, 0.5], ["0404", 0, "MIL", 1, "2-1", "3-1", 2, 0.5], ["0403", 0, "WSN", 1, "11-2", "2-1", 2, 1.0], ["0402", 0, "WSN", 0, "3-6", "1-1", 2, 1.0], ["0331", 0, "WSN", 1, "2-0", "1-0", 1, 0.5], [null, null, null, null, null, null, null, null]]}, [["20110409", "PHI", "ATL", 0, 10, 2], ["20110408", "ATL", "PHI", 1, 6, 3], ["20101003", "ATL", "PHI", 1, 8, 7], ["20101002", "PHI", "ATL", 0, 7, 0], ["20101001", "PHI", "ATL", 0, 11, 5], ["20100922", "PHI", "ATL", 1, 1, 0], ["20100921", "PHI", "ATL", 1, 5, 3], ["20100920", "PHI", "ATL", 1, 3, 1], ["20100707", "ATL", "PHI", 0, 7, 5], ["20100706", "ATL", "PHI", 0, 6, 3]]], ["ATL201104120", {"Team name": "Marlins", "Home": "3-3", "Road": "2-1", "ExtrInn": "1-2", "vsRHP": "4-1", "vsLHP": "1-3", "1-Run": "2-0", "vsEast": "3-3", "vsCntrl": "2-1", "vsWest": "0-0", "IL": "0-0", "last_10_game": [["0410", 0, "HOU", 0, "1-7", "5-4", 2, 2.0], ["0409", 0, "HOU", 1, "7-5", "5-3", 2, 1.0], ["0408", 0, "HOU", 1, "4-3", "4-3", 2, 1.0], ["0407", 1, "WSN", 0, "3-5", "3-3", 2, 2.0], ["0406", 1, "WSN", 1, "7-4", "3-2", 2, 1.0], ["0405", 1, "WSN", 1, "3-2", "2-2", 4, 1.0], ["0403", 1, "NYM", 0, "2-9", "1-2", 4, 2.0], ["0402", 1, "NYM", 0, "4-6", "1-1", 2, 1.0], ["0401", 1, "NYM", 1, "6-2", "1-0", 1, 0.0], [null, null, null, null, null, null, null, null]]}, {"Team name": "Braves", "Home": "1-2", "Road": "3-4", "ExtrInn": "0-0", "vsRHP": "2-4", "vsLHP": "2-2", "1-Run": "1-2", "vsEast": "3-3", "vsCntrl": "1-3", "vsWest": "0-0", "IL": "0-0", "last_10_game": [["0410", 1, "PHI", 0, "0-3", "4-6", 5, 3.5], ["0409", 1, "PHI", 0, "2-10", "4-5", 4, 2.5], ["0408", 1, "PHI", 1, "6-3", "4-4", 3, 1.5], ["0407", 0, "MIL", 0, "2-4", "3-4", 4, 2.5], ["0406", 0, "MIL", 0, "4-5", "3-3", 4, 1.5], ["0405", 0, "MIL", 0, "0-1", "3-2", 3, 0.5], ["0404", 0, "MIL", 1, "2-1", "3-1", 2, 0.5], ["0403", 0, "WSN", 1, "11-2", "2-1", 2, 1.0], ["0402", 0, "WSN", 0, "3-6", "1-1", 2, 1.0], ["0331", 0, "WSN", 1, "2-0", "1-0", 1, 0.5]]}, [["20100929", "ATL", "FLA", 1, 5, 1], ["20100928", "ATL", "FLA", 1, 3, 2], ["20100927", "ATL", "FLA", 1, 2, 1], ["20100905", "FLA", "ATL", 1, 7, 6], ["20100904", "ATL", "FLA", 0, 2, 0], ["20100903", "FLA", "ATL", 1, 6, 1], ["20100829", "ATL", "FLA", 1, 7, 6], ["20100828", "ATL", "FLA", 1, 12, 3], ["20100827", "FLA", "ATL", 0, 7, 1], ["20100725", "FLA", "ATL", 1, 5, 4]]], ["ATL201104130", {"Team name": "Marlins", "Home": "3-3", "Road": "2-2", "ExtrInn": "1-2", "vsRHP": "4-2", "vsLHP": "1-3", "1-Run": "2-0", "vsEast": "3-4", "vsCntrl": "2-1", "vsWest": "0-0", "IL": "0-0", "last_10_game": [["0412", 0, "ATL", 0, "0-5", "5-5", 2, 2.0], ["0410", 0, "HOU", 0, "1-7", "5-4", 2, 2.0], ["0409", 0, "HOU", 1, "7-5", "5-3", 2, 1.0], ["0408", 0, "HOU", 1, "4-3", "4-3", 2, 1.0], ["0407", 1, "WSN", 0, "3-5", "3-3", 2, 2.0], ["0406", 1, "WSN", 1, "7-4", "3-2", 2, 1.0], ["0405", 1, "WSN", 1, "3-2", "2-2", 4, 1.0], ["0403", 1, "NYM", 0, "2-9", "1-2", 4, 2.0], ["0402", 1, "NYM", 0, "4-6", "1-1", 2, 1.0], ["0401", 1, "NYM", 1, "6-2", "1-0", 1, 0.0]]}, {"Team name": "Braves", "Home": "2-2", "Road": "3-4", "ExtrInn": "0-0", "vsRHP": "3-4", "vsLHP": "2-2", "1-Run": "1-2", "vsEast": "4-3", "vsCntrl": "1-3", "vsWest": "0-0", "IL": "0-0", "last_10_game": [["0412", 1, "FLA", 1, "5-0", "5-6", 4, 2.5], ["0410", 1, "PHI", 0, "0-3", "4-6", 5, 3.5], ["0409", 1, "PHI", 0, "2-10", "4-5", 4, 2.5], ["0408", 1, "PHI", 1, "6-3", "4-4", 3, 1.5], ["0407", 0, "MIL", 0, "2-4", "3-4", 4, 2.5], ["0406", 0, "MIL", 0, "4-5", "3-3", 4, 1.5], ["0405", 0, "MIL", 0, "0-1", "3-2", 3, 0.5], ["0404", 0, "MIL", 1, "2-1", "3-1", 2, 0.5], ["0403", 0, "WSN", 1, "11-2", "2-1", 2, 1.0], ["0402", 0, "WSN", 0, "3-6", "1-1", 2, 1.0]]}, [["20110412", "ATL", "FLA", 1, 5, 0], ["20100929", "ATL", "FLA", 1, 5, 1], ["20100928", "ATL", "FLA", 1, 3, 2], ["20100927", "ATL", "FLA", 1, 2, 1], ["20100905", "FLA", "ATL", 1, 7, 6], ["20100904", "ATL", "FLA", 0, 2, 0], ["20100903", "FLA", "ATL", 1, 6, 1], ["20100829", "ATL", "FLA", 1, 7, 6], ["20100828", "ATL", "FLA", 1, 12, 3], ["20100827", "FLA", "ATL", 0, 7, 1]]], ["ATL201104160", {"Team name": "Mets", "Home": "1-6", "Road": "3-3", "ExtrInn": "1-1", "vsRHP": "2-8", "vsLHP": "2-1", "1-Run": "0-3", "vsEast": "4-5", "vsCntrl": "0-0", "vsWest": "0-4", "IL": "0-0", "last_10_game": [["0414", 1, "COL", 0, "4-9", "4-9", 5, 5.5], ["0414", 1, "COL", 0, "5-6", "4-8", 5, 5.5], ["0413", 1, "COL", 0, "4-5", "4-7", 5, 4.0], ["0411", 1, "COL", 0, "6-7", "4-6", 4, 3.5], ["0410", 1, "WSN", 0, "3-7", "4-5", 3, 3.0], ["0409", 1, "WSN", 1, "8-4", "4-4", 3, 2.0], ["0408", 1, "WSN", 0, "2-6", "3-4", 4, 2.0], ["0407", 0, "PHI", 0, "0-11", "3-3", 2, 2.0], ["0406", 0, "PHI", 0, "7-10", "3-2", 2, 1.0], ["0405", 0, "PHI", 1, "7-1", "3-1", 1, 0.0]]}, {"Team name": "Braves", "Home": "2-4", "Road": "3-4", "ExtrInn": "0-0", "vsRHP": "3-6", "vsLHP": "2-2", "1-Run": "1-3", "vsEast": "4-5", "vsCntrl": "1-3", "vsWest": "0-0", "IL": "0-0", "last_10_game": [["0414", 1, "FLA", 0, "5-6", "5-8", 4, 4.5], ["0413", 1, "FLA", 0, "1-5", "5-7", 4, 3.5], ["0412", 1, "FLA", 1, "5-0", "5-6", 4, 2.5], ["0410", 1, "PHI", 0, "0-3", "4-6", 5, 3.5], ["0409", 1, "PHI", 0, "2-10", "4-5", 4, 2.5], ["0408", 1, "PHI", 1, "6-3", "4-4", 3, 1.5], ["0407", 0, "MIL", 0, "2-4", "3-4", 4, 2.5], ["0406", 0, "MIL", 0, "4-5", "3-3", 4, 1.5], ["0405", 0, "MIL", 0, "0-1", "3-2", 3, 0.5], ["0404", 0, "MIL", 1, "2-1", "3-1", 2, 0.5]]}, [["20100919", "ATL", "NYM", 0, 6, 3], ["20100918", "ATL", "NYM", 0, 4, 2], ["20100917", "ATL", "NYM", 0, 6, 4], ["20100902", "NYM", "ATL", 0, 4, 2], ["20100901", "ATL", "NYM", 1, 4, 1], ["20100831", "ATL", "NYM", 1, 9, 2], ["20100830", "ATL", "NYM", 1, 9, 3], ["20100804", "ATL", "NYM", 1, 8, 3], ["20100803", "NYM", "ATL", 0, 3, 2], ["20100802", "ATL", "NYM", 1, 4, 1]]], ["ATL201104170", {"Team name": "Mets", "Home": "1-6", "Road": "3-5", "ExtrInn": "1-1", "vsRHP": "2-10", "vsLHP": "2-1", "1-Run": "0-3", "vsEast": "4-7", "vsCntrl": "0-0", "vsWest": "0-4", "IL": "0-0", "last_10_game": [["0416", 0, "ATL", 0, "0-4", "4-11", 5, 6.0], ["0416", 0, "ATL", 0, "2-4", "4-10", 5, 6.0], ["0414", 1, "COL", 0, "4-9", "4-9", 5, 5.5], ["0414", 1, "COL", 0, "5-6", "4-8", 5, 5.5], ["0413", 1, "COL", 0, "4-5", "4-7", 5, 4.0], ["0411", 1, "COL", 0, "6-7", "4-6", 4, 3.5], ["0410", 1, "WSN", 0, "3-7", "4-5", 3, 3.0], ["0409", 1, "WSN", 1, "8-4", "4-4", 3, 2.0], ["0408", 1, "WSN", 0, "2-6", "3-4", 4, 2.0], ["0407", 0, "PHI", 0, "0-11", "3-3", 2, 2.0]]}, {"Team name": "Braves", "Home": "4-4", "Road": "3-4", "ExtrInn": "0-0", "vsRHP": "5-6", "vsLHP": "2-2", "1-Run": "1-3", "vsEast": "6-5", "vsCntrl": "1-3", "vsWest": "0-0", "IL": "0-0", "last_10_game": [["0416", 1, "NYM", 1, "4-0", "7-8", 3, 3.0], ["0416", 1, "NYM", 1, "4-2", "6-8", 3, 3.0], ["0414", 1, "FLA", 0, "5-6", "5-8", 4, 4.5], ["0413", 1, "FLA", 0, "1-5", "5-7", 4, 3.5], ["0412", 1, "FLA", 1, "5-0", "5-6", 4, 2.5], ["0410", 1, "PHI", 0, "0-3", "4-6", 5, 3.5], ["0409", 1, "PHI", 0, "2-10", "4-5", 4, 2.5], ["0408", 1, "PHI", 1, "6-3", "4-4", 3, 1.5], ["0407", 0, "MIL", 0, "2-4", "3-4", 4, 2.5], ["0406", 0, "MIL", 0, "4-5", "3-3", 4, 1.5]]}, [["20110416", "ATL", "NYM", 1, 4, 0], ["20110416", "ATL", "NYM", 1, 4, 2], ["20100919", "ATL", "NYM", 0, 6, 3], ["20100918", "ATL", "NYM", 0, 4, 2], ["20100917", "ATL", "NYM", 0, 6, 4], ["20100902", "NYM", "ATL", 0, 4, 2], ["20100901", "ATL", "NYM", 1, 4, 1], ["20100831", "ATL", "NYM", 1, 9, 2], ["20100830", "ATL", "NYM", 1, 9, 3], ["20100804", "ATL", "NYM", 1, 8, 3]]], ["ATL201104290", {"Team name": "Cardinals", "Home": "6-6", "Road": "8-5", "ExtrInn": "0-2", "vsRHP": "10-7", "vsLHP": "4-4", "1-Run": "2-5", "vsEast": "2-1", "vsCntrl": "5-4", "vsWest": "7-6", "IL": "0-0", "last_10_game": [["0428", 0, "HOU", 1, "11-7", "14-11", 1, 1.0], ["0427", 0, "HOU", 1, "6-5", "13-11", 1, 0.5], ["0426", 0, "HOU", 0, "5-6", "12-11", 1, 0.0], ["0424", 1, "CIN", 1, "3-0", "12-10", 1, 0.5], ["0423", 1, "CIN", 0, "3-5", "11-10", 1, 0.0], ["0422", 1, "CIN", 1, "4-2", "11-9", 1, 0.5], ["0421", 1, "WSN", 1, "5-0", "10-9", 1, 0.0], ["0420", 1, "WSN", 1, "5-3", "9-9", 1, 0.0], ["0420", 1, "WSN", 0, "6-8", "8-9", 1, 0.0], ["0417", 0, "LAD", 0, "1-2", "8-8", 2, 1.5]]}, {"Team name": "Braves", "Home": "4-5", "Road": "9-8", "ExtrInn": "1-2", "vsRHP": "9-9", "vsLHP": "4-4", "1-Run": "1-4", "vsEast": "6-6", "vsCntrl": "1-3", "vsWest": "6-4", "IL": "0-0", "last_10_game": [["0427", 0, "SDP", 1, "7-0", "13-13", 3, 4.0], ["0426", 0, "SDP", 1, "8-2", "12-13", 3, 4.5], ["0425", 0, "SDP", 0, "3-5", "11-13", 4, 5.0], ["0424", 0, "SFG", 1, "9-6", "11-12", 4, 5.0], ["0423", 0, "SFG", 1, "5-2", "10-12", 4, 5.0], ["0422", 0, "SFG", 1, "4-1", "9-12", 4, 5.0], ["0421", 0, "LAD", 0, "3-5", "8-12", 4, 5.0], ["0420", 0, "LAD", 0, "1-6", "8-11", 4, 4.0], ["0419", 0, "LAD", 1, "10-1", "8-10", 4, 3.0], ["0418", 0, "LAD", 0, "2-4", "7-10", 4, 4.0]]}, [["20100912", "STL", "ATL", 0, 7, 3], ["20100911", "ATL", "STL", 1, 6, 3], ["20100910", "ATL", "STL", 1, 8, 6], ["20100909", "STL", "ATL", 0, 11, 4], ["20100429", "STL", "ATL", 1, 10, 4], ["20100428", "STL", "ATL", 1, 6, 0], ["20100427", "STL", "ATL", 1, 5, 4], ["20100426", "STL", "ATL", 1, 4, 3], ["20090913", "ATL", "STL", 0, 9, 2], ["20090912", "ATL", "STL", 0, 7, 6]]], ["ATL201105010", {"Team name": "Cardinals", "Home": "6-6", "Road": "10-5", "ExtrInn": "1-2", "vsRHP": "12-7", "vsLHP": "4-4", "1-Run": "3-5", "vsEast": "4-1", "vsCntrl": "5-4", "vsWest": "7-6", "IL": "0-0", "last_10_game": [["0430", 0, "ATL", 1, "3-2", "16-11", 1, 2.0], ["0429", 0, "ATL", 1, "5-3", "15-11", 1, 1.5], ["0428", 0, "HOU", 1, "11-7", "14-11", 1, 1.0], ["0427", 0, "HOU", 1, "6-5", "13-11", 1, 0.5], ["0426", 0, "HOU", 0, "5-6", "12-11", 1, 0.0], ["0424", 1, "CIN", 1, "3-0", "12-10", 1, 0.5], ["0423", 1, "CIN", 0, "3-5", "11-10", 1, 0.0], ["0422", 1, "CIN", 1, "4-2", "11-9", 1, 0.5], ["0421", 1, "WSN", 1, "5-0", "10-9", 1, 0.0], ["0420", 1, "WSN", 1, "5-3", "9-9", 1, 0.0]]}, {"Team name": "Braves", "Home": "4-7", "Road": "9-8", "ExtrInn": "1-3", "vsRHP": "9-11", "vsLHP": "4-4", "1-Run": "1-5", "vsEast": "6-6", "vsCntrl": "1-5", "vsWest": "6-4", "IL": "0-0", "last_10_game": [["0430", 1, "STL", 0, "2-3", "13-15", 3, 6.0], ["0429", 1, "STL", 0, "3-5", "13-14", 3, 5.0], ["0427", 0, "SDP", 1, "7-0", "13-13", 3, 4.0], ["0426", 0, "SDP", 1, "8-2", "12-13", 3, 4.5], ["0425", 0, "SDP", 0, "3-5", "11-13", 4, 5.0], ["0424", 0, "SFG", 1, "9-6", "11-12", 4, 5.0], ["0423", 0, "SFG", 1, "5-2", "10-12", 4, 5.0], ["0422", 0, "SFG", 1, "4-1", "9-12", 4, 5.0], ["0421", 0, "LAD", 0, "3-5", "8-12", 4, 5.0], ["0420", 0, "LAD", 0, "1-6", "8-11", 4, 4.0]]}, [["20110430", "STL", "ATL", 0, 3, 2], ["20110429", "STL", "ATL", 0, 5, 3], ["20100912", "STL", "ATL", 0, 7, 3], ["20100911", "ATL", "STL", 1, 6, 3], ["20100910", "ATL", "STL", 1, 8, 6], ["20100909", "STL", "ATL", 0, 11, 4], ["20100429", "STL", "ATL", 1, 10, 4], ["20100428", "STL", "ATL", 1, 6, 0], ["20100427", "STL", "ATL", 1, 5, 4], ["20100426", "STL", "ATL", 1, 4, 3]]], ["ATL201105020", {"Team name": "Brewers", "Home": "8-5", "Road": "5-9", "ExtrInn": "1-3", "vsRHP": "10-10", "vsLHP": "3-4", "1-Run": "4-6", "vsEast": "5-5", "vsCntrl": "8-9", "vsWest": "0-0", "IL": "0-0", "last_10_game": [["0501", 0, "HOU", 0, "0-5", "13-14", 3, 2.5], ["0430", 0, "HOU", 0, "1-2", "13-13", 3, 2.5], ["0429", 0, "HOU", 1, "5-0", "13-12", 2, 1.5], ["0427", 1, "CIN", 0, "6-7", "12-12", 3, 1.0], ["0426", 1, "CIN", 1, "3-2", "12-11", 1, 0.0], ["0425", 1, "CIN", 0, "5-9", "11-11", 3, 1.0], ["0424", 1, "HOU", 1, "4-1", "11-10", 2, 0.5], ["0423", 1, "HOU", 0, "6-9", "10-10", 3, 0.5], ["0422", 1, "HOU", 1, "14-7", "10-9", 2, 0.5], ["0420", 0, "PHI", 0, "3-4", "9-9", 1, 0.0]]}, {"Team name": "Braves", "Home": "5-7", "Road": "9-8", "ExtrInn": "1-3", "vsRHP": "9-11", "vsLHP": "5-4", "1-Run": "2-5", "vsEast": "6-6", "vsCntrl": "2-5", "vsWest": "6-4", "IL": "0-0", "last_10_game": [["0501", 1, "STL", 1, "6-5", "14-15", 3, 5.0], ["0430", 1, "STL", 0, "2-3", "13-15", 3, 6.0], ["0429", 1, "STL", 0, "3-5", "13-14", 3, 5.0], ["0427", 0, "SDP", 1, "7-0", "13-13", 3, 4.0], ["0426", 0, "SDP", 1, "8-2", "12-13", 3, 4.5], ["0425", 0, "SDP", 0, "3-5", "11-13", 4, 5.0], ["0424", 0, "SFG", 1, "9-6", "11-12", 4, 5.0], ["0423", 0, "SFG", 1, "5-2", "10-12", 4, 5.0], ["0422", 0, "SFG", 1, "4-1", "9-12", 4, 5.0], ["0421", 0, "LAD", 0, "3-5", "8-12", 4, 5.0]]}, [["20110407", "MIL", "ATL", 1, 4, 2], ["20110406", "MIL", "ATL", 1, 5, 4], ["20110405", "MIL", "ATL", 1, 1, 0], ["20110404", "ATL", "MIL", 0, 2, 1], ["20100718", "ATL", "MIL", 1, 11, 6], ["20100717", "MIL", "ATL", 0, 6, 3], ["20100716", "MIL", "ATL", 0, 9, 3], ["20100715", "ATL", "MIL", 1, 2, 1], ["20100512", "ATL", "MIL", 0, 9, 2], ["20100511", "ATL", "MIL", 0, 11, 3]]], ["ATL201105030", {"Team name": "Brewers", "Home": "8-5", "Road": "5-10", "ExtrInn": "1-3", "vsRHP": "10-11", "vsLHP": "3-4", "1-Run": "4-6", "vsEast": "5-6", "vsCntrl": "8-9", "vsWest": "0-0", "IL": "0-0", "last_10_game": [["0502", 0, "ATL", 0, "2-6", "13-15", 4, 2.5], ["0501", 0, "HOU", 0, "0-5", "13-14", 3, 2.5], ["0430", 0, "HOU", 0, "1-2", "13-13", 3, 2.5], ["0429", 0, "HOU", 1, "5-0", "13-12", 2, 1.5], ["0427", 1, "CIN", 0, "6-7", "12-12", 3, 1.0], ["0426", 1, "CIN", 1, "3-2", "12-11", 1, 0.0], ["0425", 1, "CIN", 0, "5-9", "11-11", 3, 1.0], ["0424", 1, "HOU", 1, "4-1", "11-10", 2, 0.5], ["0423", 1, "HOU", 0, "6-9", "10-10", 3, 0.5], ["0422", 1, "HOU", 1, "14-7", "10-9", 2, 0.5]]}, {"Team name": "Braves", "Home": "6-7", "Road": "9-8", "ExtrInn": "1-3", "vsRHP": "10-11", "vsLHP": "5-4", "1-Run": "2-5", "vsEast": "6-6", "vsCntrl": "3-5", "vsWest": "6-4", "IL": "0-0", "last_10_game": [["0502", 1, "MIL", 1, "6-2", "15-15", 3, 4.5], ["0501", 1, "STL", 1, "6-5", "14-15", 3, 5.0], ["0430", 1, "STL", 0, "2-3", "13-15", 3, 6.0], ["0429", 1, "STL", 0, "3-5", "13-14", 3, 5.0], ["0427", 0, "SDP", 1, "7-0", "13-13", 3, 4.0], ["0426", 0, "SDP", 1, "8-2", "12-13", 3, 4.5], ["0425", 0, "SDP", 0, "3-5", "11-13", 4, 5.0], ["0424", 0, "SFG", 1, "9-6", "11-12", 4, 5.0], ["0423", 0, "SFG", 1, "5-2", "10-12", 4, 5.0], ["0422", 0, "SFG", 1, "4-1", "9-12", 4, 5.0]]}, [["20110502", "ATL", "MIL", 1, 6, 2], ["20110407", "MIL", "ATL", 1, 4, 2], ["20110406", "MIL", "ATL", 1, 5, 4], ["20110405", "MIL", "ATL", 1, 1, 0], ["20110404", "ATL", "MIL", 0, 2, 1], ["20100718", "ATL", "MIL", 1, 11, 6], ["20100717", "MIL", "ATL", 0, 6, 3], ["20100716", "MIL", "ATL", 0, 9, 3], ["20100715", "ATL", "MIL", 1, 2, 1], ["20100512", "ATL", "MIL", 0, 9, 2]]], ["ATL201105040", {"Team name": "Brewers", "Home": "8-5", "Road": "5-10", "ExtrInn": "1-3", "vsRHP": "10-11", "vsLHP": "3-4", "1-Run": "4-6", "vsEast": "5-6", "vsCntrl": "8-9", "vsWest": "0-0", "IL": "0-0", "last_10_game": [["0502", 0, "ATL", 0, "2-6", "13-15", 4, 2.5], ["0501", 0, "HOU", 0, "0-5", "13-14", 3, 2.5], ["0430", 0, "HOU", 0, "1-2", "13-13", 3, 2.5], ["0429", 0, "HOU", 1, "5-0", "13-12", 2, 1.5], ["0427", 1, "CIN", 0, "6-7", "12-12", 3, 1.0], ["0426", 1, "CIN", 1, "3-2", "12-11", 1, 0.0], ["0425", 1, "CIN", 0, "5-9", "11-11", 3, 1.0], ["0424", 1, "HOU", 1, "4-1", "11-10", 2, 0.5], ["0423", 1, "HOU", 0, "6-9", "10-10", 3, 0.5], ["0422", 1, "HOU", 1, "14-7", "10-9", 2, 0.5]]}, {"Team name": "Braves", "Home": "6-7", "Road": "9-8", "ExtrInn": "1-3", "vsRHP": "10-11", "vsLHP": "5-4", "1-Run": "2-5", "vsEast": "6-6", "vsCntrl": "3-5", "vsWest": "6-4", "IL": "0-0", "last_10_game": [["0502", 1, "MIL", 1, "6-2", "15-15", 3, 4.5], ["0501", 1, "STL", 1, "6-5", "14-15", 3, 5.0], ["0430", 1, "STL", 0, "2-3", "13-15", 3, 6.0], ["0429", 1, "STL", 0, "3-5", "13-14", 3, 5.0], ["0427", 0, "SDP", 1, "7-0", "13-13", 3, 4.0], ["0426", 0, "SDP", 1, "8-2", "12-13", 3, 4.5], ["0425", 0, "SDP", 0, "3-5", "11-13", 4, 5.0], ["0424", 0, "SFG", 1, "9-6", "11-12", 4, 5.0], ["0423", 0, "SFG", 1, "5-2", "10-12", 4, 5.0], ["0422", 0, "SFG", 1, "4-1", "9-12", 4, 5.0]]}, [["20110502", "ATL", "MIL", 1, 6, 2], ["20110407", "MIL", "ATL", 1, 4, 2], ["20110406", "MIL", "ATL", 1, 5, 4], ["20110405", "MIL", "ATL", 1, 1, 0], ["20110404", "ATL", "MIL", 0, 2, 1], ["20100718", "ATL", "MIL", 1, 11, 6], ["20100717", "MIL", "ATL", 0, 6, 3], ["20100716", "MIL", "ATL", 0, 9, 3], ["20100715", "ATL", "MIL", 1, 2, 1], ["20100512", "ATL", "MIL", 0, 9, 2]]], ["ATL201105050", {"Team name": "Brewers", "Home": "8-5", "Road": "5-12", "ExtrInn": "1-3", "vsRHP": "10-13", "vsLHP": "3-4", "1-Run": "4-6", "vsEast": "5-8", "vsCntrl": "8-9", "vsWest": "0-0", "IL": "0-0", "last_10_game": [["0504", 0, "ATL", 0, "0-8", "13-17", 5, 3.5], ["0504", 0, "ATL", 0, "3-8", "13-16", 5, 3.5], ["0502", 0, "ATL", 0, "2-6", "13-15", 4, 2.5], ["0501", 0, "HOU", 0, "0-5", "13-14", 3, 2.5], ["0430", 0, "HOU", 0, "1-2", "13-13", 3, 2.5], ["0429", 0, "HOU", 1, "5-0", "13-12", 2, 1.5], ["0427", 1, "CIN", 0, "6-7", "12-12", 3, 1.0], ["0426", 1, "CIN", 1, "3-2", "12-11", 1, 0.0], ["0425", 1, "CIN", 0, "5-9", "11-11", 3, 1.0], ["0424", 1, "HOU", 1, "4-1", "11-10", 2, 0.5]]}, {"Team name": "Braves", "Home": "8-7", "Road": "9-8", "ExtrInn": "1-3", "vsRHP": "12-11", "vsLHP": "5-4", "1-Run": "2-5", "vsEast": "6-6", "vsCntrl": "5-5", "vsWest": "6-4", "IL": "0-0", "last_10_game": [["0504", 1, "MIL", 1, "8-0", "17-15", 3, 4.5], ["0504", 1, "MIL", 1, "8-3", "16-15", 3, 4.5], ["0502", 1, "MIL", 1, "6-2", "15-15", 3, 4.5], ["0501", 1, "STL", 1, "6-5", "14-15", 3, 5.0], ["0430", 1, "STL", 0, "2-3", "13-15", 3, 6.0], ["0429", 1, "STL", 0, "3-5", "13-14", 3, 5.0], ["0427", 0, "SDP", 1, "7-0", "13-13", 3, 4.0], ["0426", 0, "SDP", 1, "8-2", "12-13", 3, 4.5], ["0425", 0, "SDP", 0, "3-5", "11-13", 4, 5.0], ["0424", 0, "SFG", 1, "9-6", "11-12", 4, 5.0]]}, [["20110504", "ATL", "MIL", 1, 8, 0], ["20110504", "ATL", "MIL", 1, 8, 3], ["20110502", "ATL", "MIL", 1, 6, 2], ["20110407", "MIL", "ATL", 1, 4, 2], ["20110406", "MIL", "ATL", 1, 5, 4], ["20110405", "MIL", "ATL", 1, 1, 0], ["20110404", "ATL", "MIL", 0, 2, 1], ["20100718", "ATL", "MIL", 1, 11, 6], ["20100717", "MIL", "ATL", 0, 6, 3], ["20100716", "MIL", "ATL", 0, 9, 3]]], ["ATL201105100", {"Team name": "Nationals", "Home": "9-7", "Road": "7-11", "ExtrInn": "4-1", "vsRHP": "13-12", "vsLHP": "3-6", "1-Run": "3-3", "vsEast": "8-13", "vsCntrl": "5-4", "vsWest": "3-1", "IL": "0-0", "last_10_game": [["0508", 0, "FLA", 0, "0-8", "16-18", 4, 6.5], ["0507", 0, "FLA", 1, "5-2", "16-17", 4, 6.5], ["0506", 0, "FLA", 1, "3-2", "15-17", 4, 6.5], ["0505", 0, "PHI", 0, "3-7", "14-17", 4, 7.5], ["0504", 0, "PHI", 0, "4-7", "14-16", 4, 6.5], ["0503", 0, "PHI", 0, "1-4", "14-15", 4, 5.5], ["0502", 1, "SFG", 1, "2-0", "14-14", 3, 4.5], ["0501", 1, "SFG", 1, "5-2", "13-14", 3, 5.0], ["0430", 1, "SFG", 0, "1-2", "12-14", 3, 6.0], ["0429", 1, "SFG", 1, "3-0", "12-13", 3, 5.0]]}, {"Team name": "Braves", "Home": "9-7", "Road": "11-9", "ExtrInn": "1-3", "vsRHP": "13-12", "vsLHP": "7-4", "1-Run": "3-5", "vsEast": "8-7", "vsCntrl": "6-5", "vsWest": "6-4", "IL": "0-0", "last_10_game": [["0508", 0, "PHI", 1, "5-2", "20-16", 3, 3.5], ["0507", 0, "PHI", 0, "0-3", "19-16", 3, 4.5], ["0506", 0, "PHI", 1, "5-0", "19-15", 3, 3.5], ["0505", 1, "MIL", 1, "2-1", "18-15", 3, 4.5], ["0504", 1, "MIL", 1, "8-0", "17-15", 3, 4.5], ["0504", 1, "MIL", 1, "8-3", "16-15", 3, 4.5], ["0502", 1, "MIL", 1, "6-2", "15-15", 3, 4.5], ["0501", 1, "STL", 1, "6-5", "14-15", 3, 5.0], ["0430", 1, "STL", 0, "2-3", "13-15", 3, 6.0], ["0429", 1, "STL", 0, "3-5", "13-14", 3, 5.0]]}, [["20110403", "ATL", "WSN", 0, 11, 2], ["20110402", "WSN", "ATL", 1, 6, 3], ["20110331", "ATL", "WSN", 0, 2, 0], ["20100926", "WSN", "ATL", 1, 4, 2], ["20100925", "ATL", "WSN", 0, 5, 0], ["20100924", "WSN", "ATL", 1, 8, 3], ["20100915", "WSN", "ATL", 0, 4, 2], ["20100914", "WSN", "ATL", 0, 6, 0], ["20100913", "ATL", "WSN", 1, 4, 0], ["20100819", "WSN", "ATL", 0, 6, 2]]], ["ATL201105110", {"Team name": "Nationals", "Home": "9-7", "Road": "8-11", "ExtrInn": "4-1", "vsRHP": "14-12", "vsLHP": "3-6", "1-Run": "4-3", "vsEast": "9-13", "vsCntrl": "5-4", "vsWest": "3-1", "IL": "0-0", "last_10_game": [["0510", 0, "ATL", 1, "7-6", "17-18", 4, 6.0], ["0508", 0, "FLA", 0, "0-8", "16-18", 4, 6.5], ["0507", 0, "FLA", 1, "5-2", "16-17", 4, 6.5], ["0506", 0, "FLA", 1, "3-2", "15-17", 4, 6.5], ["0505", 0, "PHI", 0, "3-7", "14-17", 4, 7.5], ["0504", 0, "PHI", 0, "4-7", "14-16", 4, 6.5], ["0503", 0, "PHI", 0, "1-4", "14-15", 4, 5.5], ["0502", 1, "SFG", 1, "2-0", "14-14", 3, 4.5], ["0501", 1, "SFG", 1, "5-2", "13-14", 3, 5.0], ["0430", 1, "SFG", 0, "1-2", "12-14", 3, 6.0]]}, {"Team name": "Braves", "Home": "9-8", "Road": "11-9", "ExtrInn": "1-3", "vsRHP": "13-13", "vsLHP": "7-4", "1-Run": "3-6", "vsEast": "8-8", "vsCntrl": "6-5", "vsWest": "6-4", "IL": "0-0", "last_10_game": [["0510", 1, "WSN", 0, "6-7", "20-17", 3, 4.0], ["0508", 0, "PHI", 1, "5-2", "20-16", 3, 3.5], ["0507", 0, "PHI", 0, "0-3", "19-16", 3, 4.5], ["0506", 0, "PHI", 1, "5-0", "19-15", 3, 3.5], ["0505", 1, "MIL", 1, "2-1", "18-15", 3, 4.5], ["0504", 1, "MIL", 1, "8-0", "17-15", 3, 4.5], ["0504", 1, "MIL", 1, "8-3", "16-15", 3, 4.5], ["0502", 1, "MIL", 1, "6-2", "15-15", 3, 4.5], ["0501", 1, "STL", 1, "6-5", "14-15", 3, 5.0], ["0430", 1, "STL", 0, "2-3", "13-15", 3, 6.0]]}, [["20110510", "WSN", "ATL", 0, 7, 6], ["20110403", "ATL", "WSN", 0, 11, 2], ["20110402", "WSN", "ATL", 1, 6, 3], ["20110331", "ATL", "WSN", 0, 2, 0], ["20100926", "WSN", "ATL", 1, 4, 2], ["20100925", "ATL", "WSN", 0, 5, 0], ["20100924", "WSN", "ATL", 1, 8, 3], ["20100915", "WSN", "ATL", 0, 4, 2], ["20100914", "WSN", "ATL", 0, 6, 0], ["20100913", "ATL", "WSN", 1, 4, 0]]], ["ATL201105120", {"Team name": "Nationals", "Home": "9-7", "Road": "9-11", "ExtrInn": "5-1", "vsRHP": "15-12", "vsLHP": "3-6", "1-Run": "4-3", "vsEast": "10-13", "vsCntrl": "5-4", "vsWest": "3-1", "IL": "0-0", "last_10_game": [["0511", 0, "ATL", 1, "7-3", "18-18", 4, 6.0], ["0510", 0, "ATL", 1, "7-6", "17-18", 4, 6.0], ["0508", 0, "FLA", 0, "0-8", "16-18", 4, 6.5], ["0507", 0, "FLA", 1, "5-2", "16-17", 4, 6.5], ["0506", 0, "FLA", 1, "3-2", "15-17", 4, 6.5], ["0505", 0, "PHI", 0, "3-7", "14-17", 4, 7.5], ["0504", 0, "PHI", 0, "4-7", "14-16", 4, 6.5], ["0503", 0, "PHI", 0, "1-4", "14-15", 4, 5.5], ["0502", 1, "SFG", 1, "2-0", "14-14", 3, 4.5], ["0501", 1, "SFG", 1, "5-2", "13-14", 3, 5.0]]}, {"Team name": "Braves", "Home": "9-9", "Road": "11-9", "ExtrInn": "1-4", "vsRHP": "13-13", "vsLHP": "7-5", "1-Run": "3-6", "vsEast": "8-9", "vsCntrl": "6-5", "vsWest": "6-4", "IL": "0-0", "last_10_game": [["0511", 1, "WSN", 0, "3-7", "20-18", 3, 5.0], ["0510", 1, "WSN", 0, "6-7", "20-17", 3, 4.0], ["0508", 0, "PHI", 1, "5-2", "20-16", 3, 3.5], ["0507", 0, "PHI", 0, "0-3", "19-16", 3, 4.5], ["0506", 0, "PHI", 1, "5-0", "19-15", 3, 3.5], ["0505", 1, "MIL", 1, "2-1", "18-15", 3, 4.5], ["0504", 1, "MIL", 1, "8-0", "17-15", 3, 4.5], ["0504", 1, "MIL", 1, "8-3", "16-15", 3, 4.5], ["0502", 1, "MIL", 1, "6-2", "15-15", 3, 4.5], ["0501", 1, "STL", 1, "6-5", "14-15", 3, 5.0]]}, [["20110511", "WSN", "ATL", 0, 7, 3], ["20110510", "WSN", "ATL", 0, 7, 6], ["20110403", "ATL", "WSN", 0, 11, 2], ["20110402", "WSN", "ATL", 1, 6, 3], ["20110331", "ATL", "WSN", 0, 2, 0], ["20100926", "WSN", "ATL", 1, 4, 2], ["20100925", "ATL", "WSN", 0, 5, 0], ["20100924", "WSN", "ATL", 1, 8, 3], ["20100915", "WSN", "ATL", 0, 4, 2], ["20100914", "WSN", "ATL", 0, 6, 0]]], ["ATL201105130", {"Team name": "Phillies", "Home": "13-7", "Road": "11-5", "ExtrInn": "1-2", "vsRHP": "15-11", "vsLHP": "9-1", "1-Run": "5-3", "vsEast": "15-8", "vsCntrl": "4-2", "vsWest": "5-2", "IL": "0-0", "last_10_game": [["0511", 0, "FLA", 1, "5-3", "24-12", 1, 3.0], ["0510", 0, "FLA", 0, "1-2", "23-12", 1, 2.0], ["0509", 0, "FLA", 1, "6-4", "23-11", 1, 3.0], ["0508", 1, "ATL", 0, "2-5", "22-11", 1, 2.0], ["0507", 1, "ATL", 1, "3-0", "22-10", 1, 3.0], ["0506", 1, "ATL", 0, "0-5", "21-10", 1, 2.0], ["0505", 1, "WSN", 1, "7-3", "21-9", 1, 2.0], ["0504", 1, "WSN", 1, "7-4", "20-9", 1, 1.0], ["0503", 1, "WSN", 1, "4-1", "19-9", 1, 1.0], ["0501", 1, "NYM", 0, "1-2", "18-9", 1, 0.5]]}, {"Team name": "Braves", "Home": "10-9", "Road": "11-9", "ExtrInn": "2-4", "vsRHP": "14-13", "vsLHP": "7-5", "1-Run": "4-6", "vsEast": "9-9", "vsCntrl": "6-5", "vsWest": "6-4", "IL": "0-0", "last_10_game": [["0512", 1, "WSN", 1, "6-5", "21-18", 3, 4.5], ["0511", 1, "WSN", 0, "3-7", "20-18", 3, 5.0], ["0510", 1, "WSN", 0, "6-7", "20-17", 3, 4.0], ["0508", 0, "PHI", 1, "5-2", "20-16", 3, 3.5], ["0507", 0, "PHI", 0, "0-3", "19-16", 3, 4.5], ["0506", 0, "PHI", 1, "5-0", "19-15", 3, 3.5], ["0505", 1, "MIL", 1, "2-1", "18-15", 3, 4.5], ["0504", 1, "MIL", 1, "8-0", "17-15", 3, 4.5], ["0504", 1, "MIL", 1, "8-3", "16-15", 3, 4.5], ["0502", 1, "MIL", 1, "6-2", "15-15", 3, 4.5]]}, [["20110508", "ATL", "PHI", 0, 5, 2], ["20110507", "PHI", "ATL", 1, 3, 0], ["20110506", "ATL", "PHI", 0, 5, 0], ["20110410", "PHI", "ATL", 0, 3, 0], ["20110409", "PHI", "ATL", 0, 10, 2], ["20110408", "ATL", "PHI", 1, 6, 3], ["20101003", "ATL", "PHI", 1, 8, 7], ["20101002", "PHI", "ATL", 0, 7, 0], ["20101001", "PHI", "ATL", 0, 11, 5], ["20100922", "PHI", "ATL", 1, 1, 0]]], ["ATL201105140", {"Team name": "Phillies", "Home": "13-7", "Road": "12-5", "ExtrInn": "1-2", "vsRHP": "16-11", "vsLHP": "9-1", "1-Run": "6-3", "vsEast": "16-8", "vsCntrl": "4-2", "vsWest": "5-2", "IL": "0-0", "last_10_game": [["0513", 0, "ATL", 1, "5-4", "25-12", 1, 3.0], ["0511", 0, "FLA", 1, "5-3", "24-12", 1, 3.0], ["0510", 0, "FLA", 0, "1-2", "23-12", 1, 2.0], ["0509", 0, "FLA", 1, "6-4", "23-11", 1, 3.0], ["0508", 1, "ATL", 0, "2-5", "22-11", 1, 2.0], ["0507", 1, "ATL", 1, "3-0", "22-10", 1, 3.0], ["0506", 1, "ATL", 0, "0-5", "21-10", 1, 2.0], ["0505", 1, "WSN", 1, "7-3", "21-9", 1, 2.0], ["0504", 1, "WSN", 1, "7-4", "20-9", 1, 1.0], ["0503", 1, "WSN", 1, "4-1", "19-9", 1, 1.0]]}, {"Team name": "Braves", "Home": "10-10", "Road": "11-9", "ExtrInn": "2-4", "vsRHP": "14-13", "vsLHP": "7-6", "1-Run": "4-7", "vsEast": "9-10", "vsCntrl": "6-5", "vsWest": "6-4", "IL": "0-0", "last_10_game": [["0513", 1, "PHI", 0, "4-5", "21-19", 3, 5.5], ["0512", 1, "WSN", 1, "6-5", "21-18", 3, 4.5], ["0511", 1, "WSN", 0, "3-7", "20-18", 3, 5.0], ["0510", 1, "WSN", 0, "6-7", "20-17", 3, 4.0], ["0508", 0, "PHI", 1, "5-2", "20-16", 3, 3.5], ["0507", 0, "PHI", 0, "0-3", "19-16", 3, 4.5], ["0506", 0, "PHI", 1, "5-0", "19-15", 3, 3.5], ["0505", 1, "MIL", 1, "2-1", "18-15", 3, 4.5], ["0504", 1, "MIL", 1, "8-0", "17-15", 3, 4.5], ["0504", 1, "MIL", 1, "8-3", "16-15", 3, 4.5]]}, [["20110513", "PHI", "ATL", 0, 5, 4], ["20110508", "ATL", "PHI", 0, 5, 2], ["20110507", "PHI", "ATL", 1, 3, 0], ["20110506", "ATL", "PHI", 0, 5, 0], ["20110410", "PHI", "ATL", 0, 3, 0], ["20110409", "PHI", "ATL", 0, 10, 2], ["20110408", "ATL", "PHI", 1, 6, 3], ["20101003", "ATL", "PHI", 1, 8, 7], ["20101002", "PHI", "ATL", 0, 7, 0], ["20101001", "PHI", "ATL", 0, 11, 5]]], ["ATL201105150", {"Team name": "Phillies", "Home": "13-7", "Road": "12-6", "ExtrInn": "1-2", "vsRHP": "16-12", "vsLHP": "9-1", "1-Run": "6-3", "vsEast": "16-9", "vsCntrl": "4-2", "vsWest": "5-2", "IL": "0-0", "last_10_game": [["0514", 0, "ATL", 0, "3-5", "25-13", 1, 2.0], ["0513", 0, "ATL", 1, "5-4", "25-12", 1, 3.0], ["0511", 0, "FLA", 1, "5-3", "24-12", 1, 3.0], ["0510", 0, "FLA", 0, "1-2", "23-12", 1, 2.0], ["0509", 0, "FLA", 1, "6-4", "23-11", 1, 3.0], ["0508", 1, "ATL", 0, "2-5", "22-11", 1, 2.0], ["0507", 1, "ATL", 1, "3-0", "22-10", 1, 3.0], ["0506", 1, "ATL", 0, "0-5", "21-10", 1, 2.0], ["0505", 1, "WSN", 1, "7-3", "21-9", 1, 2.0], ["0504", 1, "WSN", 1, "7-4", "20-9", 1, 1.0]]}, {"Team name": "Braves", "Home": "11-10", "Road": "11-9", "ExtrInn": "2-4", "vsRHP": "15-13", "vsLHP": "7-6", "1-Run": "4-7", "vsEast": "10-10", "vsCntrl": "6-5", "vsWest": "6-4", "IL": "0-0", "last_10_game": [["0514", 1, "PHI", 1, "5-3", "22-19", 3, 4.5], ["0513", 1, "PHI", 0, "4-5", "21-19", 3, 5.5], ["0512", 1, "WSN", 1, "6-5", "21-18", 3, 4.5], ["0511", 1, "WSN", 0, "3-7", "20-18", 3, 5.0], ["0510", 1, "WSN", 0, "6-7", "20-17", 3, 4.0], ["0508", 0, "PHI", 1, "5-2", "20-16", 3, 3.5], ["0507", 0, "PHI", 0, "0-3", "19-16", 3, 4.5], ["0506", 0, "PHI", 1, "5-0", "19-15", 3, 3.5], ["0505", 1, "MIL", 1, "2-1", "18-15", 3, 4.5], ["0504", 1, "MIL", 1, "8-0", "17-15", 3, 4.5]]}, [["20110514", "ATL", "PHI", 1, 5, 3], ["20110513", "PHI", "ATL", 0, 5, 4], ["20110508", "ATL", "PHI", 0, 5, 2], ["20110507", "PHI", "ATL", 1, 3, 0], ["20110506", "ATL", "PHI", 0, 5, 0], ["20110410", "PHI", "ATL", 0, 3, 0], ["20110409", "PHI", "ATL", 0, 10, 2], ["20110408", "ATL", "PHI", 1, 6, 3], ["20101003", "ATL", "PHI", 1, 8, 7], ["20101002", "PHI", "ATL", 0, 7, 0]]], ["ATL201105160", {"Team name": "Astros", "Home": "9-13", "Road": "6-12", "ExtrInn": "1-0", "vsRHP": "9-18", "vsLHP": "6-7", "1-Run": "7-6", "vsEast": "4-8", "vsCntrl": "9-15", "vsWest": "2-2", "IL": "0-0", "last_10_game": [["0515", 1, "NYM", 0, "4-7", "15-25", 6, 8.0], ["0514", 1, "NYM", 1, "7-3", "15-24", 6, 7.0], ["0513", 1, "NYM", 0, "4-6", "14-24", 6, 7.5], ["0511", 1, "CIN", 1, "4-3", "14-23", 6, 7.0], ["0510", 1, "CIN", 0, "3-7", "13-23", 6, 8.0], ["0509", 1, "CIN", 0, "1-6", "13-22", 6, 7.0], ["0508", 0, "PIT", 0, "4-5", "13-21", 6, 6.5], ["0507", 0, "PIT", 0, "1-6", "13-20", 6, 5.5], ["0506", 0, "PIT", 1, "3-2", "13-19", 5, 5.5], ["0505", 0, "CIN", 0, "4-10", "12-19", 6, 5.5]]}, {"Team name": "Braves", "Home": "12-10", "Road": "11-9", "ExtrInn": "2-4", "vsRHP": "16-13", "vsLHP": "7-6", "1-Run": "5-7", "vsEast": "11-10", "vsCntrl": "6-5", "vsWest": "6-4", "IL": "0-0", "last_10_game": [["0515", 1, "PHI", 1, "3-2", "23-19", 3, 3.5], ["0514", 1, "PHI", 1, "5-3", "22-19", 3, 4.5], ["0513", 1, "PHI", 0, "4-5", "21-19", 3, 5.5], ["0512", 1, "WSN", 1, "6-5", "21-18", 3, 4.5], ["0511", 1, "WSN", 0, "3-7", "20-18", 3, 5.0], ["0510", 1, "WSN", 0, "6-7", "20-17", 3, 4.0], ["0508", 0, "PHI", 1, "5-2", "20-16", 3, 3.5], ["0507", 0, "PHI", 0, "0-3", "19-16", 3, 4.5], ["0506", 0, "PHI", 1, "5-0", "19-15", 3, 3.5], ["0505", 1, "MIL", 1, "2-1", "18-15", 3, 4.5]]}, [["20100811", "ATL", "HOU", 0, 8, 2], ["20100810", "ATL", "HOU", 0, 4, 2], ["20100809", "HOU", "ATL", 1, 10, 4], ["20100502", "ATL", "HOU", 1, 7, 1], ["20100501", "ATL", "HOU", 1, 10, 1], ["20100430", "ATL", "HOU", 1, 4, 2], ["20090910", "ATL", "HOU", 0, 9, 7], ["20090909", "HOU", "ATL", 1, 2, 1], ["20090908", "ATL", "HOU", 0, 2, 1], ["20090503", "HOU", "ATL", 0, 7, 5]]], ["ATL201105170", {"Team name": "Astros", "Home": "9-13", "Road": "6-13", "ExtrInn": "1-0", "vsRHP": "9-19", "vsLHP": "6-7", "1-Run": "7-7", "vsEast": "4-9", "vsCntrl": "9-15", "vsWest": "2-2", "IL": "0-0", "last_10_game": [["0516", 0, "ATL", 0, "2-3", "15-26", 6, 9.0], ["0515", 1, "NYM", 0, "4-7", "15-25", 6, 8.0], ["0514", 1, "NYM", 1, "7-3", "15-24", 6, 7.0], ["0513", 1, "NYM", 0, "4-6", "14-24", 6, 7.5], ["0511", 1, "CIN", 1, "4-3", "14-23", 6, 7.0], ["0510", 1, "CIN", 0, "3-7", "13-23", 6, 8.0], ["0509", 1, "CIN", 0, "1-6", "13-22", 6, 7.0], ["0508", 0, "PIT", 0, "4-5", "13-21", 6, 6.5], ["0507", 0, "PIT", 0, "1-6", "13-20", 6, 5.5], ["0506", 0, "PIT", 1, "3-2", "13-19", 5, 5.5]]}, {"Team name": "Braves", "Home": "13-10", "Road": "11-9", "ExtrInn": "2-4", "vsRHP": "17-13", "vsLHP": "7-6", "1-Run": "6-7", "vsEast": "11-10", "vsCntrl": "7-5", "vsWest": "6-4", "IL": "0-0", "last_10_game": [["0516", 1, "HOU", 1, "3-2", "24-19", 3, 2.5], ["0515", 1, "PHI", 1, "3-2", "23-19", 3, 3.5], ["0514", 1, "PHI", 1, "5-3", "22-19", 3, 4.5], ["0513", 1, "PHI", 0, "4-5", "21-19", 3, 5.5], ["0512", 1, "WSN", 1, "6-5", "21-18", 3, 4.5], ["0511", 1, "WSN", 0, "3-7", "20-18", 3, 5.0], ["0510", 1, "WSN", 0, "6-7", "20-17", 3, 4.0], ["0508", 0, "PHI", 1, "5-2", "20-16", 3, 3.5], ["0507", 0, "PHI", 0, "0-3", "19-16", 3, 4.5], ["0506", 0, "PHI", 1, "5-0", "19-15", 3, 3.5]]}, [["20110516", "ATL", "HOU", 1, 3, 2], ["20100811", "ATL", "HOU", 0, 8, 2], ["20100810", "ATL", "HOU", 0, 4, 2], ["20100809", "HOU", "ATL", 1, 10, 4], ["20100502", "ATL", "HOU", 1, 7, 1], ["20100501", "ATL", "HOU", 1, 10, 1], ["20100430", "ATL", "HOU", 1, 4, 2], ["20090910", "ATL", "HOU", 0, 9, 7], ["20090909", "HOU", "ATL", 1, 2, 1], ["20090908", "ATL", "HOU", 0, 2, 1]]], ["ATL201105270", {"Team name": "Reds", "Home": "15-11", "Road": "11-14", "ExtrInn": "4-1", "vsRHP": "22-20", "vsLHP": "4-5", "1-Run": "7-11", "vsEast": "2-5", "vsCntrl": "20-12", "vsWest": "4-5", "IL": "0-3", "last_10_game": [["0526", 0, "PHI", 0, "4-10", "26-25", 3, 4.0], ["0525", 0, "PHI", 0, "4-5", "26-24", 3, 3.5], ["0524", 0, "PHI", 1, "6-3", "26-23", 2, 3.5], ["0523", 0, "PHI", 0, "3-10", "25-23", 2, 3.5], ["0522", 0, "CLE", 0, "4-12", "25-22", 2, 2.5], ["0521", 0, "CLE", 0, "1-2", "25-21", 2, 1.5], ["0520", 0, "CLE", 0, "4-5", "25-20", 2, 0.5], ["0519", 1, "PIT", 0, "3-5", "25-19", 2, 0.5], ["0518", 1, "PIT", 0, "0-5", "25-18", 1, 0.5], ["0517", 1, "CHC", 1, "7-5", "25-17", 1, 1.5]]}, {"Team name": "Braves", "Home": "14-10", "Road": "14-13", "ExtrInn": "5-5", "vsRHP": "20-16", "vsLHP": "8-7", "1-Run": "7-9", "vsEast": "11-10", "vsCntrl": "10-5", "vsWest": "6-6", "IL": "1-2", "last_10_game": [["0525", 0, "PIT", 1, "4-2", "28-23", 3, 3.0], ["0524", 0, "PIT", 1, "2-0", "27-23", 3, 3.0], ["0522", 0, "LAA", 0, "1-4", "26-23", 3, 3.5], ["0521", 0, "LAA", 1, "5-4", "26-22", 3, 3.5], ["0520", 0, "LAA", 0, "0-9", "25-22", 3, 3.5], ["0519", 0, "ARI", 0, "1-2", "25-21", 3, 2.5], ["0518", 0, "ARI", 0, "4-5", "25-20", 3, 2.5], ["0517", 1, "HOU", 1, "3-1", "25-19", 3, 1.5], ["0516", 1, "HOU", 1, "3-2", "24-19", 3, 2.5], ["0515", 1, "PHI", 1, "3-2", "23-19", 3, 3.5]]}, [["20100801", "CIN", "ATL", 1, 2, 1], ["20100731", "CIN", "ATL", 1, 5, 2], ["20100730", "ATL", "CIN", 0, 6, 4], ["20100520", "ATL", "CIN", 1, 10, 9], ["20100519", "ATL", "CIN", 1, 5, 4], ["20090906", "CIN", "ATL", 0, 4, 2], ["20090905", "CIN", "ATL", 0, 3, 1], ["20090904", "CIN", "ATL", 0, 3, 1], ["20090618", "ATL", "CIN", 0, 7, 0], ["20090617", "CIN", "ATL", 1, 4, 3]]], ["ATL201105280", {"Team name": "Reds", "Home": "15-11", "Road": "12-14", "ExtrInn": "4-1", "vsRHP": "23-20", "vsLHP": "4-5", "1-Run": "7-11", "vsEast": "3-5", "vsCntrl": "20-12", "vsWest": "4-5", "IL": "0-3", "last_10_game": [["0527", 0, "ATL", 1, "5-1", "27-25", 3, 4.0], ["0526", 0, "PHI", 0, "4-10", "26-25", 3, 4.0], ["0525", 0, "PHI", 0, "4-5", "26-24", 3, 3.5], ["0524", 0, "PHI", 1, "6-3", "26-23", 2, 3.5], ["0523", 0, "PHI", 0, "3-10", "25-23", 2, 3.5], ["0522", 0, "CLE", 0, "4-12", "25-22", 2, 2.5], ["0521", 0, "CLE", 0, "1-2", "25-21", 2, 1.5], ["0520", 0, "CLE", 0, "4-5", "25-20", 2, 0.5], ["0519", 1, "PIT", 0, "3-5", "25-19", 2, 0.5], ["0518", 1, "PIT", 0, "0-5", "25-18", 1, 0.5]]}, {"Team name": "Braves", "Home": "14-11", "Road": "14-13", "ExtrInn": "5-5", "vsRHP": "20-17", "vsLHP": "8-7", "1-Run": "7-9", "vsEast": "11-10", "vsCntrl": "10-6", "vsWest": "6-6", "IL": "1-2", "last_10_game": [["0527", 1, "CIN", 0, "1-5", "28-24", 3, 4.5], ["0525", 0, "PIT", 1, "4-2", "28-23", 3, 3.0], ["0524", 0, "PIT", 1, "2-0", "27-23", 3, 3.0], ["0522", 0, "LAA", 0, "1-4", "26-23", 3, 3.5], ["0521", 0, "LAA", 1, "5-4", "26-22", 3, 3.5], ["0520", 0, "LAA", 0, "0-9", "25-22", 3, 3.5], ["0519", 0, "ARI", 0, "1-2", "25-21", 3, 2.5], ["0518", 0, "ARI", 0, "4-5", "25-20", 3, 2.5], ["0517", 1, "HOU", 1, "3-1", "25-19", 3, 1.5], ["0516", 1, "HOU", 1, "3-2", "24-19", 3, 2.5]]}, [["20110527", "CIN", "ATL", 0, 5, 1], ["20100801", "CIN", "ATL", 1, 2, 1], ["20100731", "CIN", "ATL", 1, 5, 2], ["20100730", "ATL", "CIN", 0, 6, 4], ["20100520", "ATL", "CIN", 1, 10, 9], ["20100519", "ATL", "CIN", 1, 5, 4], ["20090906", "CIN", "ATL", 0, 4, 2], ["20090905", "CIN", "ATL", 0, 3, 1], ["20090904", "CIN", "ATL", 0, 3, 1], ["20090618", "ATL", "CIN", 0, 7, 0]]], ["ATL201105290", {"Team name": "Reds", "Home": "15-11", "Road": "12-15", "ExtrInn": "4-2", "vsRHP": "23-21", "vsLHP": "4-5", "1-Run": "7-12", "vsEast": "3-6", "vsCntrl": "20-12", "vsWest": "4-5", "IL": "0-3", "last_10_game": [["0528", 0, "ATL", 0, "6-7", "27-26", 3, 4.0], ["0527", 0, "ATL", 1, "5-1", "27-25", 3, 4.0], ["0526", 0, "PHI", 0, "4-10", "26-25", 3, 4.0], ["0525", 0, "PHI", 0, "4-5", "26-24", 3, 3.5], ["0524", 0, "PHI", 1, "6-3", "26-23", 2, 3.5], ["0523", 0, "PHI", 0, "3-10", "25-23", 2, 3.5], ["0522", 0, "CLE", 0, "4-12", "25-22", 2, 2.5], ["0521", 0, "CLE", 0, "1-2", "25-21", 2, 1.5], ["0520", 0, "CLE", 0, "4-5", "25-20", 2, 0.5], ["0519", 1, "PIT", 0, "3-5", "25-19", 2, 0.5]]}, {"Team name": "Braves", "Home": "15-11", "Road": "14-13", "ExtrInn": "6-5", "vsRHP": "21-17", "vsLHP": "8-7", "1-Run": "8-9", "vsEast": "11-10", "vsCntrl": "11-6", "vsWest": "6-6", "IL": "1-2", "last_10_game": [["0528", 1, "CIN", 1, "7-6", "29-24", 3, 4.5], ["0527", 1, "CIN", 0, "1-5", "28-24", 3, 4.5], ["0525", 0, "PIT", 1, "4-2", "28-23", 3, 3.0], ["0524", 0, "PIT", 1, "2-0", "27-23", 3, 3.0], ["0522", 0, "LAA", 0, "1-4", "26-23", 3, 3.5], ["0521", 0, "LAA", 1, "5-4", "26-22", 3, 3.5], ["0520", 0, "LAA", 0, "0-9", "25-22", 3, 3.5], ["0519", 0, "ARI", 0, "1-2", "25-21", 3, 2.5], ["0518", 0, "ARI", 0, "4-5", "25-20", 3, 2.5], ["0517", 1, "HOU", 1, "3-1", "25-19", 3, 1.5]]}, [["20110528", "ATL", "CIN", 1, 7, 6], ["20110527", "CIN", "ATL", 0, 5, 1], ["20100801", "CIN", "ATL", 1, 2, 1], ["20100731", "CIN", "ATL", 1, 5, 2], ["20100730", "ATL", "CIN", 0, 6, 4], ["20100520", "ATL", "CIN", 1, 10, 9], ["20100519", "ATL", "CIN", 1, 5, 4], ["20090906", "CIN", "ATL", 0, 4, 2], ["20090905", "CIN", "ATL", 0, 3, 1], ["20090904", "CIN", "ATL", 0, 3, 1]]], ["ATL201105300", {"Team name": "Padres", "Home": "9-20", "Road": "13-11", "ExtrInn": "3-6", "vsRHP": "15-24", "vsLHP": "7-7", "1-Run": "8-9", "vsEast": "3-7", "vsCntrl": "10-14", "vsWest": "9-7", "IL": "0-3", "last_10_game": [["0529", 0, "WSN", 1, "5-4", "22-31", 5, 7.0], ["0528", 0, "WSN", 1, "2-1", "21-31", 5, 7.5], ["0527", 0, "WSN", 0, "1-2", "20-31", 5, 8.5], ["0525", 1, "STL", 1, "3-1", "20-30", 5, 8.0], ["0524", 1, "STL", 0, "2-3", "19-30", 5, 9.0], ["0523", 1, "STL", 0, "1-3", "19-29", 5, 9.0], ["0522", 1, "SEA", 0, "1-6", "19-28", 5, 8.5], ["0521", 1, "SEA", 0, "0-4", "19-27", 5, 7.5], ["0520", 1, "SEA", 0, "1-4", "19-26", 5, 6.5], ["0519", 1, "MIL", 1, "1-0", "19-25", 5, 5.5]]}, {"Team name": "Braves", "Home": "16-11", "Road": "14-13", "ExtrInn": "6-5", "vsRHP": "22-17", "vsLHP": "8-7", "1-Run": "9-9", "vsEast": "11-10", "vsCntrl": "12-6", "vsWest": "6-6", "IL": "1-2", "last_10_game": [["0529", 1, "CIN", 1, "2-1", "30-24", 3, 3.5], ["0528", 1, "CIN", 1, "7-6", "29-24", 3, 4.5], ["0527", 1, "CIN", 0, "1-5", "28-24", 3, 4.5], ["0525", 0, "PIT", 1, "4-2", "28-23", 3, 3.0], ["0524", 0, "PIT", 1, "2-0", "27-23", 3, 3.0], ["0522", 0, "LAA", 0, "1-4", "26-23", 3, 3.5], ["0521", 0, "LAA", 1, "5-4", "26-22", 3, 3.5], ["0520", 0, "LAA", 0, "0-9", "25-22", 3, 3.5], ["0519", 0, "ARI", 0, "1-2", "25-21", 3, 2.5], ["0518", 0, "ARI", 0, "4-5", "25-20", 3, 2.5]]}, [["20110427", "ATL", "SDP", 0, 7, 0], ["20110426", "ATL", "SDP", 0, 8, 2], ["20110425", "SDP", "ATL", 1, 5, 3], ["20100722", "ATL", "SDP", 1, 8, 0], ["20100721", "SDP", "ATL", 0, 6, 4], ["20100720", "ATL", "SDP", 1, 4, 1], ["20100415", "ATL", "SDP", 0, 6, 2], ["20100414", "ATL", "SDP", 0, 6, 1], ["20100412", "SDP", "ATL", 1, 17, 2], ["20090827", "ATL", "SDP", 1, 9, 1]]], ["ATL201106010", {"Team name": "Padres", "Home": "9-20", "Road": "15-11", "ExtrInn": "4-6", "vsRHP": "16-24", "vsLHP": "8-7", "1-Run": "10-9", "vsEast": "5-7", "vsCntrl": "10-14", "vsWest": "9-7", "IL": "0-3", "last_10_game": [["0531", 0, "ATL", 1, "5-4", "24-31", 5, 6.0], ["0530", 0, "ATL", 1, "3-2", "23-31", 5, 7.0], ["0529", 0, "WSN", 1, "5-4", "22-31", 5, 7.0], ["0528", 0, "WSN", 1, "2-1", "21-31", 5, 7.5], ["0527", 0, "WSN", 0, "1-2", "20-31", 5, 8.5], ["0525", 1, "STL", 1, "3-1", "20-30", 5, 8.0], ["0524", 1, "STL", 0, "2-3", "19-30", 5, 9.0], ["0523", 1, "STL", 0, "1-3", "19-29", 5, 9.0], ["0522", 1, "SEA", 0, "1-6", "19-28", 5, 8.5], ["0521", 1, "SEA", 0, "0-4", "19-27", 5, 7.5]]}, {"Team name": "Braves", "Home": "16-13", "Road": "14-13", "ExtrInn": "6-6", "vsRHP": "22-19", "vsLHP": "8-7", "1-Run": "9-11", "vsEast": "11-10", "vsCntrl": "12-6", "vsWest": "6-8", "IL": "1-2", "last_10_game": [["0531", 1, "SDP", 0, "4-5", "30-26", 3, 4.5], ["0530", 1, "SDP", 0, "2-3", "30-25", 3, 4.5], ["0529", 1, "CIN", 1, "2-1", "30-24", 3, 3.5], ["0528", 1, "CIN", 1, "7-6", "29-24", 3, 4.5], ["0527", 1, "CIN", 0, "1-5", "28-24", 3, 4.5], ["0525", 0, "PIT", 1, "4-2", "28-23", 3, 3.0], ["0524", 0, "PIT", 1, "2-0", "27-23", 3, 3.0], ["0522", 0, "LAA", 0, "1-4", "26-23", 3, 3.5], ["0521", 0, "LAA", 1, "5-4", "26-22", 3, 3.5], ["0520", 0, "LAA", 0, "0-9", "25-22", 3, 3.5]]}, [["20110531", "SDP", "ATL", 0, 5, 4], ["20110530", "SDP", "ATL", 0, 3, 2], ["20110427", "ATL", "SDP", 0, 7, 0], ["20110426", "ATL", "SDP", 0, 8, 2], ["20110425", "SDP", "ATL", 1, 5, 3], ["20100722", "ATL", "SDP", 1, 8, 0], ["20100721", "SDP", "ATL", 0, 6, 4], ["20100720", "ATL", "SDP", 1, 4, 1], ["20100415", "ATL", "SDP", 0, 6, 2], ["20100414", "ATL", "SDP", 0, 6, 1]]], ["ATL201106140", {"Team name": "Mets", "Home": "15-17", "Road": "17-17", "ExtrInn": "2-3", "vsRHP": "23-27", "vsLHP": "9-7", "1-Run": "7-11", "vsEast": "13-14", "vsCntrl": "10-10", "vsWest": "8-8", "IL": "1-2", "last_10_game": [["0613", 0, "PIT", 0, "1-3", "32-34", 4, 8.0], ["0612", 0, "PIT", 1, "7-0", "32-33", 4, 7.5], ["0611", 0, "PIT", 0, "2-3", "31-33", 4, 7.5], ["0610", 0, "PIT", 1, "8-1", "31-32", 4, 6.5], ["0609", 0, "MIL", 1, "4-1", "30-32", 4, 6.5], ["0608", 0, "MIL", 0, "6-7", "29-32", 4, 7.5], ["0607", 0, "MIL", 1, "2-1", "29-31", 4, 6.5], ["0605", 1, "ATL", 1, "6-4", "28-31", 4, 7.0], ["0604", 1, "ATL", 1, "5-0", "27-31", 4, 7.0], ["0603", 1, "ATL", 0, "3-6", "26-31", 4, 8.0]]}, {"Team name": "Braves", "Home": "17-13", "Road": "21-16", "ExtrInn": "8-6", "vsRHP": "27-21", "vsLHP": "11-8", "1-Run": "13-11", "vsEast": "15-12", "vsCntrl": "15-7", "vsWest": "7-8", "IL": "1-2", "last_10_game": [["0613", 0, "HOU", 0, "3-8", "38-29", 2, 2.5], ["0612", 0, "HOU", 1, "4-1", "38-28", 2, 2.0], ["0611", 0, "HOU", 1, "6-3", "37-28", 2, 2.0], ["0610", 0, "HOU", 1, "11-4", "36-28", 2, 2.0], ["0609", 0, "FLA", 1, "3-2", "35-28", 2, 2.0], ["0608", 0, "FLA", 1, "3-2", "34-28", 2, 3.0], ["0607", 0, "FLA", 1, "1-0", "33-28", 2, 3.0], ["0605", 0, "NYM", 0, "4-6", "32-28", 3, 3.5], ["0604", 0, "NYM", 0, "0-5", "32-27", 3, 2.5], ["0603", 0, "NYM", 1, "6-3", "32-26", 3, 2.5]]}, [["20110605", "NYM", "ATL", 1, 6, 4], ["20110604", "NYM", "ATL", 1, 5, 0], ["20110603", "ATL", "NYM", 0, 6, 3], ["20110417", "NYM", "ATL", 0, 3, 2], ["20110416", "ATL", "NYM", 1, 4, 0], ["20110416", "ATL", "NYM", 1, 4, 2], ["20100919", "ATL", "NYM", 0, 6, 3], ["20100918", "ATL", "NYM", 0, 4, 2], ["20100917", "ATL", "NYM", 0, 6, 4], ["20100902", "NYM", "ATL", 0, 4, 2]]], ["ATL201106150", {"Team name": "Mets", "Home": "15-17", "Road": "18-17", "ExtrInn": "2-3", "vsRHP": "24-27", "vsLHP": "9-7", "1-Run": "8-11", "vsEast": "14-14", "vsCntrl": "10-10", "vsWest": "8-8", "IL": "1-2", "last_10_game": [["0614", 0, "ATL", 1, "4-3", "33-34", 3, 8.0], ["0613", 0, "PIT", 0, "1-3", "32-34", 4, 8.0], ["0612", 0, "PIT", 1, "7-0", "32-33", 4, 7.5], ["0611", 0, "PIT", 0, "2-3", "31-33", 4, 7.5], ["0610", 0, "PIT", 1, "8-1", "31-32", 4, 6.5], ["0609", 0, "MIL", 1, "4-1", "30-32", 4, 6.5], ["0608", 0, "MIL", 0, "6-7", "29-32", 4, 7.5], ["0607", 0, "MIL", 1, "2-1", "29-31", 4, 6.5], ["0605", 1, "ATL", 1, "6-4", "28-31", 4, 7.0], ["0604", 1, "ATL", 1, "5-0", "27-31", 4, 7.0]]}, {"Team name": "Braves", "Home": "17-14", "Road": "21-16", "ExtrInn": "8-6", "vsRHP": "27-21", "vsLHP": "11-9", "1-Run": "13-12", "vsEast": "15-13", "vsCntrl": "15-7", "vsWest": "7-8", "IL": "1-2", "last_10_game": [["0614", 1, "NYM", 0, "3-4", "38-30", 2, 3.5], ["0613", 0, "HOU", 0, "3-8", "38-29", 2, 2.5], ["0612", 0, "HOU", 1, "4-1", "38-28", 2, 2.0], ["0611", 0, "HOU", 1, "6-3", "37-28", 2, 2.0], ["0610", 0, "HOU", 1, "11-4", "36-28", 2, 2.0], ["0609", 0, "FLA", 1, "3-2", "35-28", 2, 2.0], ["0608", 0, "FLA", 1, "3-2", "34-28", 2, 3.0], ["0607", 0, "FLA", 1, "1-0", "33-28", 2, 3.0], ["0605", 0, "NYM", 0, "4-6", "32-28", 3, 3.5], ["0604", 0, "NYM", 0, "0-5", "32-27", 3, 2.5]]}, [["20110614", "NYM", "ATL", 0, 4, 3], ["20110605", "NYM", "ATL", 1, 6, 4], ["20110604", "NYM", "ATL", 1, 5, 0], ["20110603", "ATL", "NYM", 0, 6, 3], ["20110417", "NYM", "ATL", 0, 3, 2], ["20110416", "ATL", "NYM", 1, 4, 0], ["20110416", "ATL", "NYM", 1, 4, 2], ["20100919", "ATL", "NYM", 0, 6, 3], ["20100918", "ATL", "NYM", 0, 4, 2], ["20100917", "ATL", "NYM", 0, 6, 4]]], ["ATL201106160", {"Team name": "Mets", "Home": "15-17", "Road": "19-17", "ExtrInn": "2-3", "vsRHP": "25-27", "vsLHP": "9-7", "1-Run": "8-11", "vsEast": "15-14", "vsCntrl": "10-10", "vsWest": "8-8", "IL": "1-2", "last_10_game": [["0615", 0, "ATL", 1, "4-0", "34-34", 3, 8.5], ["0614", 0, "ATL", 1, "4-3", "33-34", 3, 8.0], ["0613", 0, "PIT", 0, "1-3", "32-34", 4, 8.0], ["0612", 0, "PIT", 1, "7-0", "32-33", 4, 7.5], ["0611", 0, "PIT", 0, "2-3", "31-33", 4, 7.5], ["0610", 0, "PIT", 1, "8-1", "31-32", 4, 6.5], ["0609", 0, "MIL", 1, "4-1", "30-32", 4, 6.5], ["0608", 0, "MIL", 0, "6-7", "29-32", 4, 7.5], ["0607", 0, "MIL", 1, "2-1", "29-31", 4, 6.5], ["0605", 1, "ATL", 1, "6-4", "28-31", 4, 7.0]]}, {"Team name": "Braves", "Home": "17-15", "Road": "21-16", "ExtrInn": "8-6", "vsRHP": "27-22", "vsLHP": "11-9", "1-Run": "13-12", "vsEast": "15-14", "vsCntrl": "15-7", "vsWest": "7-8", "IL": "1-2", "last_10_game": [["0615", 1, "NYM", 0, "0-4", "38-31", 2, 5.0], ["0614", 1, "NYM", 0, "3-4", "38-30", 2, 3.5], ["0613", 0, "HOU", 0, "3-8", "38-29", 2, 2.5], ["0612", 0, "HOU", 1, "4-1", "38-28", 2, 2.0], ["0611", 0, "HOU", 1, "6-3", "37-28", 2, 2.0], ["0610", 0, "HOU", 1, "11-4", "36-28", 2, 2.0], ["0609", 0, "FLA", 1, "3-2", "35-28", 2, 2.0], ["0608", 0, "FLA", 1, "3-2", "34-28", 2, 3.0], ["0607", 0, "FLA", 1, "1-0", "33-28", 2, 3.0], ["0605", 0, "NYM", 0, "4-6", "32-28", 3, 3.5]]}, [["20110615", "NYM", "ATL", 0, 4, 0], ["20110614", "NYM", "ATL", 0, 4, 3], ["20110605", "NYM", "ATL", 1, 6, 4], ["20110604", "NYM", "ATL", 1, 5, 0], ["20110603", "ATL", "NYM", 0, 6, 3], ["20110417", "NYM", "ATL", 0, 3, 2], ["20110416", "ATL", "NYM", 1, 4, 0], ["20110416", "ATL", "NYM", 1, 4, 2], ["20100919", "ATL", "NYM", 0, 6, 3], ["20100918", "ATL", "NYM", 0, 4, 2]]], ["ATL201107040", {"Team name": "Rockies", "Home": "22-22", "Road": "19-21", "ExtrInn": "1-5", "vsRHP": "26-32", "vsLHP": "15-11", "1-Run": "12-15", "vsEast": "7-5", "vsCntrl": "9-10", "vsWest": "17-21", "IL": "8-7", "last_10_game": [["0703", 1, "KCR", 0, "8-16", "41-43", 3, 6.5], ["0702", 1, "KCR", 1, "9-6", "41-42", 3, 6.5], ["0701", 1, "KCR", 1, "9-0", "40-42", 3, 6.5], ["0630", 1, "CHW", 0, "4-6", "39-42", 3, 6.5], ["0629", 1, "CHW", 0, "2-3", "39-41", 3, 6.5], ["0628", 1, "CHW", 1, "3-2", "39-40", 3, 6.5], ["0627", 0, "CHC", 0, "3-7", "38-40", 3, 6.0], ["0626", 0, "NYY", 0, "4-6", "38-39", 3, 5.5], ["0625", 0, "NYY", 0, "3-8", "38-38", 3, 4.5], ["0624", 0, "NYY", 1, "4-2", "38-37", 3, 4.0]]}, {"Team name": "Braves", "Home": "24-18", "Road": "25-18", "ExtrInn": "9-7", "vsRHP": "35-24", "vsLHP": "14-12", "1-Run": "16-14", "vsEast": "16-14", "vsCntrl": "15-7", "vsWest": "8-10", "IL": "10-5", "last_10_game": [["0703", 1, "BAL", 0, "4-5", "49-36", 2, 4.0], ["0702", 1, "BAL", 1, "5-4", "49-35", 2, 4.0], ["0701", 1, "BAL", 1, "4-0", "48-35", 2, 4.0], ["0629", 0, "SEA", 1, "5-3", "47-35", 2, 4.5], ["0628", 0, "SEA", 1, "5-4", "46-35", 2, 4.5], ["0627", 0, "SEA", 1, "3-1", "45-35", 2, 4.5], ["0626", 0, "SDP", 0, "1-4", "44-35", 2, 5.0], ["0625", 0, "SDP", 1, "10-1", "44-34", 2, 4.0], ["0624", 0, "SDP", 0, "2-11", "43-34", 2, 5.0], ["0622", 1, "TOR", 1, "5-1", "43-33", 2, 4.5]]}, [["20100825", "COL", "ATL", 1, 12, 10], ["20100824", "COL", "ATL", 1, 5, 2], ["20100823", "COL", "ATL", 1, 5, 4], ["20100418", "ATL", "COL", 1, 4, 3], ["20100417", "COL", "ATL", 0, 4, 0], ["20100416", "ATL", "COL", 1, 9, 5], ["20090712", "COL", "ATL", 1, 8, 7], ["20090711", "ATL", "COL", 0, 4, 3], ["20090710", "ATL", "COL", 0, 4, 1], ["20090709", "COL", "ATL", 1, 7, 6]]], ["ATL201107060", {"Team name": "Rockies", "Home": "22-22", "Road": "19-23", "ExtrInn": "1-5", "vsRHP": "26-34", "vsLHP": "15-11", "1-Run": "12-15", "vsEast": "7-7", "vsCntrl": "9-10", "vsWest": "17-21", "IL": "8-7", "last_10_game": [["0705", 0, "ATL", 0, "3-5", "41-45", 3, 6.5], ["0704", 0, "ATL", 0, "1-4", "41-44", 3, 6.5], ["0703", 1, "KCR", 0, "8-16", "41-43", 3, 6.5], ["0702", 1, "KCR", 1, "9-6", "41-42", 3, 6.5], ["0701", 1, "KCR", 1, "9-0", "40-42", 3, 6.5], ["0630", 1, "CHW", 0, "4-6", "39-42", 3, 6.5], ["0629", 1, "CHW", 0, "2-3", "39-41", 3, 6.5], ["0628", 1, "CHW", 1, "3-2", "39-40", 3, 6.5], ["0627", 0, "CHC", 0, "3-7", "38-40", 3, 6.0], ["0626", 0, "NYY", 0, "4-6", "38-39", 3, 5.5]]}, {"Team name": "Braves", "Home": "26-18", "Road": "25-18", "ExtrInn": "9-7", "vsRHP": "37-24", "vsLHP": "14-12", "1-Run": "16-14", "vsEast": "16-14", "vsCntrl": "15-7", "vsWest": "10-10", "IL": "10-5", "last_10_game": [["0705", 1, "COL", 1, "5-3", "51-36", 2, 4.0], ["0704", 1, "COL", 1, "4-1", "50-36", 2, 4.0], ["0703", 1, "BAL", 0, "4-5", "49-36", 2, 4.0], ["0702", 1, "BAL", 1, "5-4", "49-35", 2, 4.0], ["0701", 1, "BAL", 1, "4-0", "48-35", 2, 4.0], ["0629", 0, "SEA", 1, "5-3", "47-35", 2, 4.5], ["0628", 0, "SEA", 1, "5-4", "46-35", 2, 4.5], ["0627", 0, "SEA", 1, "3-1", "45-35", 2, 4.5], ["0626", 0, "SDP", 0, "1-4", "44-35", 2, 5.0], ["0625", 0, "SDP", 1, "10-1", "44-34", 2, 4.0]]}, [["20110705", "ATL", "COL", 1, 5, 3], ["20110704", "ATL", "COL", 1, 4, 1], ["20100825", "COL", "ATL", 1, 12, 10], ["20100824", "COL", "ATL", 1, 5, 2], ["20100823", "COL", "ATL", 1, 5, 4], ["20100418", "ATL", "COL", 1, 4, 3], ["20100417", "COL", "ATL", 0, 4, 0], ["20100416", "ATL", "COL", 1, 9, 5], ["20090712", "COL", "ATL", 1, 8, 7], ["20090711", "ATL", "COL", 0, 4, 3]]], ["ATL201107150", {"Team name": "Nationals", "Home": "28-18", "Road": "18-28", "ExtrInn": "9-5", "vsRHP": "33-36", "vsLHP": "13-10", "1-Run": "18-18", "vsEast": "13-19", "vsCntrl": "14-10", "vsWest": "11-10", "IL": "8-7", "last_10_game": [["0710", 1, "COL", 1, "2-0", "46-46", 4, 11.5], ["0709", 1, "COL", 0, "1-2", "45-46", 4, 11.5], ["0708", 1, "COL", 0, "2-3", "45-45", 4, 11.5], ["0707", 1, "CHC", 0, "9-10", "45-44", 4, 10.5], ["0706", 1, "CHC", 1, "5-4", "45-43", 4, 10.0], ["0705", 1, "CHC", 1, "3-2", "44-43", 4, 11.0], ["0704", 1, "CHC", 1, "5-4", "43-43", 4, 11.0], ["0703", 1, "PIT", 0, "2-10", "42-43", 4, 11.0], ["0702", 1, "PIT", 1, "4-3", "42-42", 3, 11.0], ["0702", 1, "PIT", 0, "3-5", "41-42", 3, 11.0]]}, {"Team name": "Braves", "Home": "28-18", "Road": "26-20", "ExtrInn": "10-8", "vsRHP": "39-25", "vsLHP": "15-13", "1-Run": "16-15", "vsEast": "17-16", "vsCntrl": "15-7", "vsWest": "12-10", "IL": "10-5", "last_10_game": [["0710", 0, "PHI", 0, "1-14", "54-38", 2, 3.5], ["0709", 0, "PHI", 1, "4-1", "54-37", 2, 2.5], ["0708", 0, "PHI", 0, "2-3", "53-37", 2, 3.5], ["0707", 1, "COL", 1, "6-3", "53-36", 2, 2.5], ["0706", 1, "COL", 1, "9-1", "52-36", 2, 3.0], ["0705", 1, "COL", 1, "5-3", "51-36", 2, 4.0], ["0704", 1, "COL", 1, "4-1", "50-36", 2, 4.0], ["0703", 1, "BAL", 0, "4-5", "49-36", 2, 4.0], ["0702", 1, "BAL", 1, "5-4", "49-35", 2, 4.0], ["0701", 1, "BAL", 1, "4-0", "48-35", 2, 4.0]]}, [["20110512", "ATL", "WSN", 1, 6, 5], ["20110511", "WSN", "ATL", 0, 7, 3], ["20110510", "WSN", "ATL", 0, 7, 6], ["20110403", "ATL", "WSN", 0, 11, 2], ["20110402", "WSN", "ATL", 1, 6, 3], ["20110331", "ATL", "WSN", 0, 2, 0], ["20100926", "WSN", "ATL", 1, 4, 2], ["20100925", "ATL", "WSN", 0, 5, 0], ["20100924", "WSN", "ATL", 1, 8, 3], ["20100915", "WSN", "ATL", 0, 4, 2]]], ["ATL201107160", {"Team name": "Nationals", "Home": "28-18", "Road": "18-29", "ExtrInn": "9-5", "vsRHP": "33-37", "vsLHP": "13-10", "1-Run": "18-18", "vsEast": "13-20", "vsCntrl": "14-10", "vsWest": "11-10", "IL": "8-7", "last_10_game": [["0715", 0, "ATL", 0, "1-11", "46-47", 4, 12.5], ["0710", 1, "COL", 1, "2-0", "46-46", 4, 11.5], ["0709", 1, "COL", 0, "1-2", "45-46", 4, 11.5], ["0708", 1, "COL", 0, "2-3", "45-45", 4, 11.5], ["0707", 1, "CHC", 0, "9-10", "45-44", 4, 10.5], ["0706", 1, "CHC", 1, "5-4", "45-43", 4, 10.0], ["0705", 1, "CHC", 1, "3-2", "44-43", 4, 11.0], ["0704", 1, "CHC", 1, "5-4", "43-43", 4, 11.0], ["0703", 1, "PIT", 0, "2-10", "42-43", 4, 11.0], ["0702", 1, "PIT", 1, "4-3", "42-42", 3, 11.0]]}, {"Team name": "Braves", "Home": "29-18", "Road": "26-20", "ExtrInn": "10-8", "vsRHP": "40-25", "vsLHP": "15-13", "1-Run": "16-15", "vsEast": "18-16", "vsCntrl": "15-7", "vsWest": "12-10", "IL": "10-5", "last_10_game": [["0715", 1, "WSN", 1, "11-1", "55-38", 2, 3.5], ["0710", 0, "PHI", 0, "1-14", "54-38", 2, 3.5], ["0709", 0, "PHI", 1, "4-1", "54-37", 2, 2.5], ["0708", 0, "PHI", 0, "2-3", "53-37", 2, 3.5], ["0707", 1, "COL", 1, "6-3", "53-36", 2, 2.5], ["0706", 1, "COL", 1, "9-1", "52-36", 2, 3.0], ["0705", 1, "COL", 1, "5-3", "51-36", 2, 4.0], ["0704", 1, "COL", 1, "4-1", "50-36", 2, 4.0], ["0703", 1, "BAL", 0, "4-5", "49-36", 2, 4.0], ["0702", 1, "BAL", 1, "5-4", "49-35", 2, 4.0]]}, [["20110715", "ATL", "WSN", 1, 11, 1], ["20110512", "ATL", "WSN", 1, 6, 5], ["20110511", "WSN", "ATL", 0, 7, 3], ["20110510", "WSN", "ATL", 0, 7, 6], ["20110403", "ATL", "WSN", 0, 11, 2], ["20110402", "WSN", "ATL", 1, 6, 3], ["20110331", "ATL", "WSN", 0, 2, 0], ["20100926", "WSN", "ATL", 1, 4, 2], ["20100925", "ATL", "WSN", 0, 5, 0], ["20100924", "WSN", "ATL", 1, 8, 3]]], ["ATL201107170", {"Team name": "Nationals", "Home": "28-18", "Road": "19-29", "ExtrInn": "9-5", "vsRHP": "34-37", "vsLHP": "13-10", "1-Run": "18-18", "vsEast": "14-20", "vsCntrl": "14-10", "vsWest": "11-10", "IL": "8-7", "last_10_game": [["0716", 0, "ATL", 1, "5-2", "47-47", 4, 11.5], ["0715", 0, "ATL", 0, "1-11", "46-47", 4, 12.5], ["0710", 1, "COL", 1, "2-0", "46-46", 4, 11.5], ["0709", 1, "COL", 0, "1-2", "45-46", 4, 11.5], ["0708", 1, "COL", 0, "2-3", "45-45", 4, 11.5], ["0707", 1, "CHC", 0, "9-10", "45-44", 4, 10.5], ["0706", 1, "CHC", 1, "5-4", "45-43", 4, 10.0], ["0705", 1, "CHC", 1, "3-2", "44-43", 4, 11.0], ["0704", 1, "CHC", 1, "5-4", "43-43", 4, 11.0], ["0703", 1, "PIT", 0, "2-10", "42-43", 4, 11.0]]}, {"Team name": "Braves", "Home": "29-19", "Road": "26-20", "ExtrInn": "10-8", "vsRHP": "40-25", "vsLHP": "15-14", "1-Run": "16-15", "vsEast": "18-17", "vsCntrl": "15-7", "vsWest": "12-10", "IL": "10-5", "last_10_game": [["0716", 1, "WSN", 0, "2-5", "55-39", 2, 3.5], ["0715", 1, "WSN", 1, "11-1", "55-38", 2, 3.5], ["0710", 0, "PHI", 0, "1-14", "54-38", 2, 3.5], ["0709", 0, "PHI", 1, "4-1", "54-37", 2, 2.5], ["0708", 0, "PHI", 0, "2-3", "53-37", 2, 3.5], ["0707", 1, "COL", 1, "6-3", "53-36", 2, 2.5], ["0706", 1, "COL", 1, "9-1", "52-36", 2, 3.0], ["0705", 1, "COL", 1, "5-3", "51-36", 2, 4.0], ["0704", 1, "COL", 1, "4-1", "50-36", 2, 4.0], ["0703", 1, "BAL", 0, "4-5", "49-36", 2, 4.0]]}, [["20110716", "WSN", "ATL", 0, 5, 2], ["20110715", "ATL", "WSN", 1, 11, 1], ["20110512", "ATL", "WSN", 1, 6, 5], ["20110511", "WSN", "ATL", 0, 7, 3], ["20110510", "WSN", "ATL", 0, 7, 6], ["20110403", "ATL", "WSN", 0, 11, 2], ["20110402", "WSN", "ATL", 1, 6, 3], ["20110331", "ATL", "WSN", 0, 2, 0], ["20100926", "WSN", "ATL", 1, 4, 2], ["20100925", "ATL", "WSN", 0, 5, 0]]], ["ATL201107250", {"Team name": "Pirates", "Home": "26-25", "Road": "26-22", "ExtrInn": "5-3", "vsRHP": "34-36", "vsLHP": "18-11", "1-Run": "15-10", "vsEast": "10-14", "vsCntrl": "25-16", "vsWest": "9-10", "IL": "8-7", "last_10_game": [["0724", 1, "STL", 1, "4-3", "52-47", 1, 0.0], ["0723", 1, "STL", 0, "1-9", "51-47", 3, 1.0], ["0722", 1, "STL", 0, "4-6", "51-46", 2, 1.0], ["0720", 1, "CIN", 0, "1-3", "51-45", 2, 0.5], ["0719", 1, "CIN", 1, "1-0", "51-44", 1, 0.5], ["0718", 1, "CIN", 1, "2-0", "50-44", 1, 0.5], ["0717", 0, "HOU", 1, "7-5", "49-44", 2, 0.5], ["0716", 0, "HOU", 0, "4-6", "48-44", 3, 1.0], ["0715", 0, "HOU", 1, "4-0", "48-43", 1, 0.0], ["0710", 1, "CHC", 1, "9-1", "47-43", 3, 1.0]]}, {"Team name": "Braves", "Home": "30-19", "Road": "29-24", "ExtrInn": "10-8", "vsRHP": "43-28", "vsLHP": "16-15", "1-Run": "17-17", "vsEast": "19-17", "vsCntrl": "16-9", "vsWest": "14-12", "IL": "10-5", "last_10_game": [["0724", 0, "CIN", 0, "3-4", "59-43", 2, 6.0], ["0723", 0, "CIN", 0, "2-11", "59-42", 2, 5.0], ["0722", 0, "CIN", 1, "6-4", "59-41", 2, 4.0], ["0721", 0, "COL", 1, "9-6", "58-41", 2, 4.0], ["0720", 0, "COL", 0, "2-3", "57-41", 2, 4.5], ["0719", 0, "COL", 0, "3-12", "57-40", 2, 3.5], ["0718", 0, "COL", 1, "7-4", "57-39", 2, 2.5], ["0717", 1, "WSN", 1, "9-8", "56-39", 2, 3.5], ["0716", 1, "WSN", 0, "2-5", "55-39", 2, 3.5], ["0715", 1, "WSN", 1, "11-1", "55-38", 2, 3.5]]}, [["20110525", "ATL", "PIT", 0, 4, 2], ["20110524", "ATL", "PIT", 0, 2, 0], ["20100908", "ATL", "PIT", 0, 9, 3], ["20100907", "PIT", "ATL", 1, 5, 0], ["20100906", "PIT", "ATL", 1, 3, 1], ["20100530", "ATL", "PIT", 1, 5, 2], ["20100529", "ATL", "PIT", 1, 6, 3], ["20100528", "ATL", "PIT", 1, 7, 3], ["20100523", "PIT", "ATL", 1, 3, 2], ["20100522", "ATL", "PIT", 0, 4, 2]]], ["ATL201107270", {"Team name": "Pirates", "Home": "26-25", "Road": "27-23", "ExtrInn": "5-4", "vsRHP": "35-37", "vsLHP": "18-11", "1-Run": "15-11", "vsEast": "11-15", "vsCntrl": "25-16", "vsWest": "9-10", "IL": "8-7", "last_10_game": [["0726", 0, "ATL", 0, "3-4", "53-48", 3, 1.0], ["0725", 0, "ATL", 1, "3-1", "53-47", 1, 0.0], ["0724", 1, "STL", 1, "4-3", "52-47", 1, 0.0], ["0723", 1, "STL", 0, "1-9", "51-47", 3, 1.0], ["0722", 1, "STL", 0, "4-6", "51-46", 2, 1.0], ["0720", 1, "CIN", 0, "1-3", "51-45", 2, 0.5], ["0719", 1, "CIN", 1, "1-0", "51-44", 1, 0.5], ["0718", 1, "CIN", 1, "2-0", "50-44", 1, 0.5], ["0717", 0, "HOU", 1, "7-5", "49-44", 2, 0.5], ["0716", 0, "HOU", 0, "4-6", "48-44", 3, 1.0]]}, {"Team name": "Braves", "Home": "31-20", "Road": "29-24", "ExtrInn": "11-8", "vsRHP": "44-29", "vsLHP": "16-15", "1-Run": "18-17", "vsEast": "19-17", "vsCntrl": "17-10", "vsWest": "14-12", "IL": "10-5", "last_10_game": [["0726", 1, "PIT", 1, "4-3", "60-44", 2, 6.0], ["0725", 1, "PIT", 0, "1-3", "59-44", 2, 6.0], ["0724", 0, "CIN", 0, "3-4", "59-43", 2, 6.0], ["0723", 0, "CIN", 0, "2-11", "59-42", 2, 5.0], ["0722", 0, "CIN", 1, "6-4", "59-41", 2, 4.0], ["0721", 0, "COL", 1, "9-6", "58-41", 2, 4.0], ["0720", 0, "COL", 0, "2-3", "57-41", 2, 4.5], ["0719", 0, "COL", 0, "3-12", "57-40", 2, 3.5], ["0718", 0, "COL", 1, "7-4", "57-39", 2, 2.5], ["0717", 1, "WSN", 1, "9-8", "56-39", 2, 3.5]]}, [["20110726", "ATL", "PIT", 1, 4, 3], ["20110725", "PIT", "ATL", 0, 3, 1], ["20110525", "ATL", "PIT", 0, 4, 2], ["20110524", "ATL", "PIT", 0, 2, 0], ["20100908", "ATL", "PIT", 0, 9, 3], ["20100907", "PIT", "ATL", 1, 5, 0], ["20100906", "PIT", "ATL", 1, 3, 1], ["20100530", "ATL", "PIT", 1, 5, 2], ["20100529", "ATL", "PIT", 1, 6, 3], ["20100528", "ATL", "PIT", 1, 7, 3]]], ["ATL201107280", {"Team name": "Pirates", "Home": "26-25", "Road": "27-24", "ExtrInn": "5-5", "vsRHP": "35-38", "vsLHP": "18-11", "1-Run": "15-12", "vsEast": "11-16", "vsCntrl": "25-16", "vsWest": "9-10", "IL": "8-7", "last_10_game": [["0727", 0, "ATL", 0, "1-2", "53-49", 3, 1.5], ["0726", 0, "ATL", 0, "3-4", "53-48", 3, 1.0], ["0725", 0, "ATL", 1, "3-1", "53-47", 1, 0.0], ["0724", 1, "STL", 1, "4-3", "52-47", 1, 0.0], ["0723", 1, "STL", 0, "1-9", "51-47", 3, 1.0], ["0722", 1, "STL", 0, "4-6", "51-46", 2, 1.0], ["0720", 1, "CIN", 0, "1-3", "51-45", 2, 0.5], ["0719", 1, "CIN", 1, "1-0", "51-44", 1, 0.5], ["0718", 1, "CIN", 1, "2-0", "50-44", 1, 0.5], ["0717", 0, "HOU", 1, "7-5", "49-44", 2, 0.5]]}, {"Team name": "Braves", "Home": "32-20", "Road": "29-24", "ExtrInn": "12-8", "vsRHP": "44-29", "vsLHP": "17-15", "1-Run": "19-17", "vsEast": "19-17", "vsCntrl": "18-10", "vsWest": "14-12", "IL": "10-5", "last_10_game": [["0727", 1, "PIT", 1, "2-1", "61-44", 2, 5.0], ["0726", 1, "PIT", 1, "4-3", "60-44", 2, 6.0], ["0725", 1, "PIT", 0, "1-3", "59-44", 2, 6.0], ["0724", 0, "CIN", 0, "3-4", "59-43", 2, 6.0], ["0723", 0, "CIN", 0, "2-11", "59-42", 2, 5.0], ["0722", 0, "CIN", 1, "6-4", "59-41", 2, 4.0], ["0721", 0, "COL", 1, "9-6", "58-41", 2, 4.0], ["0720", 0, "COL", 0, "2-3", "57-41", 2, 4.5], ["0719", 0, "COL", 0, "3-12", "57-40", 2, 3.5], ["0718", 0, "COL", 1, "7-4", "57-39", 2, 2.5]]}, [["20110727", "ATL", "PIT", 1, 2, 1], ["20110726", "ATL", "PIT", 1, 4, 3], ["20110725", "PIT", "ATL", 0, 3, 1], ["20110525", "ATL", "PIT", 0, 4, 2], ["20110524", "ATL", "PIT", 0, 2, 0], ["20100908", "ATL", "PIT", 0, 9, 3], ["20100907", "PIT", "ATL", 1, 5, 0], ["20100906", "PIT", "ATL", 1, 3, 1], ["20100530", "ATL", "PIT", 1, 5, 2], ["20100529", "ATL", "PIT", 1, 6, 3]]], ["ATL201107300", {"Team name": "Marlins", "Home": "23-30", "Road": "29-24", "ExtrInn": "5-10", "vsRHP": "36-39", "vsLHP": "16-15", "1-Run": "18-21", "vsEast": "18-21", "vsCntrl": "16-11", "vsWest": "10-12", "IL": "8-10", "last_10_game": [["0729", 0, "ATL", 0, "0-5", "52-54", 4, 14.5], ["0728", 0, "WSN", 1, "5-2", "52-53", 4, 13.5], ["0727", 0, "WSN", 1, "7-5", "51-53", 4, 14.5], ["0726", 0, "WSN", 1, "11-2", "50-53", 4, 15.5], ["0724", 1, "NYM", 1, "5-4", "49-53", 5, 16.0], ["0723", 1, "NYM", 1, "8-5", "48-53", 5, 16.0], ["0722", 1, "NYM", 0, "6-7", "47-53", 5, 16.0], ["0721", 1, "SDP", 0, "3-5", "47-52", 5, 15.0], ["0720", 1, "SDP", 0, "3-14", "47-51", 5, 14.5], ["0719", 1, "SDP", 0, "0-4", "47-50", 5, 13.5]]}, {"Team name": "Braves", "Home": "33-21", "Road": "29-24", "ExtrInn": "12-8", "vsRHP": "45-30", "vsLHP": "17-15", "1-Run": "19-17", "vsEast": "20-17", "vsCntrl": "18-11", "vsWest": "14-12", "IL": "10-5", "last_10_game": [["0729", 1, "FLA", 1, "5-0", "62-45", 2, 5.0], ["0728", 1, "PIT", 0, "2-5", "61-45", 2, 5.0], ["0727", 1, "PIT", 1, "2-1", "61-44", 2, 5.0], ["0726", 1, "PIT", 1, "4-3", "60-44", 2, 6.0], ["0725", 1, "PIT", 0, "1-3", "59-44", 2, 6.0], ["0724", 0, "CIN", 0, "3-4", "59-43", 2, 6.0], ["0723", 0, "CIN", 0, "2-11", "59-42", 2, 5.0], ["0722", 0, "CIN", 1, "6-4", "59-41", 2, 4.0], ["0721", 0, "COL", 1, "9-6", "58-41", 2, 4.0], ["0720", 0, "COL", 0, "2-3", "57-41", 2, 4.5]]}, [["20110729", "ATL", "FLA", 1, 5, 0], ["20110609", "ATL", "FLA", 0, 3, 2], ["20110608", "ATL", "FLA", 0, 3, 2], ["20110607", "ATL", "FLA", 0, 1, 0], ["20110414", "FLA", "ATL", 0, 6, 5], ["20110413", "FLA", "ATL", 0, 5, 1], ["20110412", "ATL", "FLA", 1, 5, 0], ["20100929", "ATL", "FLA", 1, 5, 1], ["20100928", "ATL", "FLA", 1, 3, 2], ["20100927", "ATL", "FLA", 1, 2, 1]]], ["ATL201107310", {"Team name": "Marlins", "Home": "23-30", "Road": "29-25", "ExtrInn": "5-10", "vsRHP": "36-40", "vsLHP": "16-15", "1-Run": "18-21", "vsEast": "18-22", "vsCntrl": "16-11", "vsWest": "10-12", "IL": "8-10", "last_10_game": [["0730", 0, "ATL", 0, "1-5", "52-55", 4, 15.5], ["0729", 0, "ATL", 0, "0-5", "52-54", 4, 14.5], ["0728", 0, "WSN", 1, "5-2", "52-53", 4, 13.5], ["0727", 0, "WSN", 1, "7-5", "51-53", 4, 14.5], ["0726", 0, "WSN", 1, "11-2", "50-53", 4, 15.5], ["0724", 1, "NYM", 1, "5-4", "49-53", 5, 16.0], ["0723", 1, "NYM", 1, "8-5", "48-53", 5, 16.0], ["0722", 1, "NYM", 0, "6-7", "47-53", 5, 16.0], ["0721", 1, "SDP", 0, "3-5", "47-52", 5, 15.0], ["0720", 1, "SDP", 0, "3-14", "47-51", 5, 14.5]]}, {"Team name": "Braves", "Home": "34-21", "Road": "29-24", "ExtrInn": "12-8", "vsRHP": "46-30", "vsLHP": "17-15", "1-Run": "19-17", "vsEast": "21-17", "vsCntrl": "18-11", "vsWest": "14-12", "IL": "10-5", "last_10_game": [["0730", 1, "FLA", 1, "5-1", "63-45", 2, 5.0], ["0729", 1, "FLA", 1, "5-0", "62-45", 2, 5.0], ["0728", 1, "PIT", 0, "2-5", "61-45", 2, 5.0], ["0727", 1, "PIT", 1, "2-1", "61-44", 2, 5.0], ["0726", 1, "PIT", 1, "4-3", "60-44", 2, 6.0], ["0725", 1, "PIT", 0, "1-3", "59-44", 2, 6.0], ["0724", 0, "CIN", 0, "3-4", "59-43", 2, 6.0], ["0723", 0, "CIN", 0, "2-11", "59-42", 2, 5.0], ["0722", 0, "CIN", 1, "6-4", "59-41", 2, 4.0], ["0721", 0, "COL", 1, "9-6", "58-41", 2, 4.0]]}, [["20110730", "ATL", "FLA", 1, 5, 1], ["20110729", "ATL", "FLA", 1, 5, 0], ["20110609", "ATL", "FLA", 0, 3, 2], ["20110608", "ATL", "FLA", 0, 3, 2], ["20110607", "ATL", "FLA", 0, 1, 0], ["20110414", "FLA", "ATL", 0, 6, 5], ["20110413", "FLA", "ATL", 0, 5, 1], ["20110412", "ATL", "FLA", 1, 5, 0], ["20100929", "ATL", "FLA", 1, 5, 1], ["20100928", "ATL", "FLA", 1, 3, 2]]], ["ATL201108120", {"Team name": "Cubs", "Home": "29-33", "Road": "22-34", "ExtrInn": "6-3", "vsRHP": "38-49", "vsLHP": "13-18", "1-Run": "17-19", "vsEast": "10-13", "vsCntrl": "22-30", "vsWest": "14-14", "IL": "5-10", "last_10_game": [["0811", 1, "WSN", 1, "4-3", "51-67", 5, 16.0], ["0810", 1, "WSN", 1, "4-2", "50-67", 5, 17.0], ["0809", 1, "WSN", 0, "1-3", "49-67", 5, 17.0], ["0807", 1, "CIN", 0, "7-8", "49-66", 5, 16.0], ["0806", 1, "CIN", 1, "11-4", "49-65", 5, 15.0], ["0805", 1, "CIN", 1, "4-3", "48-65", 5, 15.0], ["0804", 0, "PIT", 1, "7-6", "47-65", 5, 15.0], ["0803", 0, "PIT", 1, "1-0", "46-65", 5, 15.5], ["0802", 0, "PIT", 1, "11-6", "45-65", 5, 15.5], ["0801", 0, "PIT", 1, "5-3", "44-65", 5, 16.5]]}, {"Team name": "Braves", "Home": "34-22", "Road": "35-27", "ExtrInn": "13-8", "vsRHP": "51-32", "vsLHP": "18-17", "1-Run": "21-17", "vsEast": "27-21", "vsCntrl": "18-11", "vsWest": "14-12", "IL": "10-5", "last_10_game": [["0810", 0, "FLA", 1, "6-2", "69-49", 2, 8.5], ["0809", 0, "FLA", 1, "4-3", "68-49", 2, 8.5], ["0808", 0, "FLA", 1, "8-5", "67-49", 2, 8.5], ["0807", 0, "NYM", 1, "6-5", "66-49", 2, 8.5], ["0806", 0, "NYM", 0, "7-11", "65-49", 2, 9.5], ["0805", 0, "NYM", 1, "4-1", "65-48", 2, 8.5], ["0803", 0, "WSN", 1, "6-4", "64-48", 2, 8.0], ["0802", 0, "WSN", 0, "3-9", "63-48", 2, 8.0], ["0801", 0, "WSN", 0, "3-5", "63-47", 2, 7.0], ["0731", 1, "FLA", 0, "1-3", "63-46", 2, 6.0]]}, [["20100822", "ATL", "CHC", 0, 16, 5], ["20100821", "CHC", "ATL", 1, 5, 4], ["20100820", "ATL", "CHC", 0, 5, 3], ["20100408", "CHC", "ATL", 0, 2, 0], ["20100407", "ATL", "CHC", 1, 3, 2], ["20100405", "ATL", "CHC", 1, 16, 5], ["20090708", "ATL", "CHC", 0, 4, 1], ["20090707", "ATL", "CHC", 0, 2, 1], ["20090706", "CHC", "ATL", 1, 4, 2], ["20090622", "ATL", "CHC", 1, 2, 0]]], ["ATL201108130", {"Team name": "Cubs", "Home": "29-33", "Road": "22-35", "ExtrInn": "6-3", "vsRHP": "38-49", "vsLHP": "13-19", "1-Run": "17-19", "vsEast": "10-14", "vsCntrl": "22-30", "vsWest": "14-14", "IL": "5-10", "last_10_game": [["0812", 0, "ATL", 0, "4-10", "51-68", 5, 17.0], ["0811", 1, "WSN", 1, "4-3", "51-67", 5, 16.0], ["0810", 1, "WSN", 1, "4-2", "50-67", 5, 17.0], ["0809", 1, "WSN", 0, "1-3", "49-67", 5, 17.0], ["0807", 1, "CIN", 0, "7-8", "49-66", 5, 16.0], ["0806", 1, "CIN", 1, "11-4", "49-65", 5, 15.0], ["0805", 1, "CIN", 1, "4-3", "48-65", 5, 15.0], ["0804", 0, "PIT", 1, "7-6", "47-65", 5, 15.0], ["0803", 0, "PIT", 1, "1-0", "46-65", 5, 15.5], ["0802", 0, "PIT", 1, "11-6", "45-65", 5, 15.5]]}, {"Team name": "Braves", "Home": "35-22", "Road": "35-27", "ExtrInn": "13-8", "vsRHP": "52-32", "vsLHP": "18-17", "1-Run": "21-17", "vsEast": "27-21", "vsCntrl": "19-11", "vsWest": "14-12", "IL": "10-5", "last_10_game": [["0812", 1, "CHC", 1, "10-4", "70-49", 2, 7.5], ["0810", 0, "FLA", 1, "6-2", "69-49", 2, 8.5], ["0809", 0, "FLA", 1, "4-3", "68-49", 2, 8.5], ["0808", 0, "FLA", 1, "8-5", "67-49", 2, 8.5], ["0807", 0, "NYM", 1, "6-5", "66-49", 2, 8.5], ["0806", 0, "NYM", 0, "7-11", "65-49", 2, 9.5], ["0805", 0, "NYM", 1, "4-1", "65-48", 2, 8.5], ["0803", 0, "WSN", 1, "6-4", "64-48", 2, 8.0], ["0802", 0, "WSN", 0, "3-9", "63-48", 2, 8.0], ["0801", 0, "WSN", 0, "3-5", "63-47", 2, 7.0]]}, [["20110812", "ATL", "CHC", 1, 10, 4], ["20100822", "ATL", "CHC", 0, 16, 5], ["20100821", "CHC", "ATL", 1, 5, 4], ["20100820", "ATL", "CHC", 0, 5, 3], ["20100408", "CHC", "ATL", 0, 2, 0], ["20100407", "ATL", "CHC", 1, 3, 2], ["20100405", "ATL", "CHC", 1, 16, 5], ["20090708", "ATL", "CHC", 0, 4, 1], ["20090707", "ATL", "CHC", 0, 2, 1], ["20090706", "CHC", "ATL", 1, 4, 2]]], ["ATL201108150", {"Team name": "Giants", "Home": "35-25", "Road": "31-30", "ExtrInn": "10-6", "vsRHP": "46-44", "vsLHP": "20-11", "1-Run": "28-16", "vsEast": "12-17", "vsCntrl": "16-16", "vsWest": "28-17", "IL": "10-5", "last_10_game": [["0814", 0, "FLA", 1, "5-2", "66-55", 2, 2.0], ["0813", 0, "FLA", 1, "3-0", "65-55", 2, 2.0], ["0812", 0, "FLA", 0, "1-2", "64-55", 2, 2.0], ["0810", 1, "PIT", 0, "2-9", "64-54", 2, 0.5], ["0809", 1, "PIT", 1, "6-0", "64-53", 1, 0.5], ["0808", 1, "PIT", 0, "0-5", "63-53", 1, 0.5], ["0807", 1, "PHI", 1, "3-1", "63-52", 1, 0.5], ["0806", 1, "PHI", 0, "1-2", "62-52", 1, 0.5], ["0805", 1, "PHI", 0, "2-9", "62-51", 1, 0.5], ["0804", 1, "PHI", 0, "0-3", "62-50", 1, 0.5]]}, {"Team name": "Braves", "Home": "35-24", "Road": "35-27", "ExtrInn": "13-8", "vsRHP": "52-34", "vsLHP": "18-17", "1-Run": "21-18", "vsEast": "27-21", "vsCntrl": "19-13", "vsWest": "14-12", "IL": "10-5", "last_10_game": [["0814", 1, "CHC", 0, "5-6", "70-51", 2, 9.0], ["0813", 1, "CHC", 0, "4-8", "70-50", 2, 8.5], ["0812", 1, "CHC", 1, "10-4", "70-49", 2, 7.5], ["0810", 0, "FLA", 1, "6-2", "69-49", 2, 8.5], ["0809", 0, "FLA", 1, "4-3", "68-49", 2, 8.5], ["0808", 0, "FLA", 1, "8-5", "67-49", 2, 8.5], ["0807", 0, "NYM", 1, "6-5", "66-49", 2, 8.5], ["0806", 0, "NYM", 0, "7-11", "65-49", 2, 9.5], ["0805", 0, "NYM", 1, "4-1", "65-48", 2, 8.5], ["0803", 0, "WSN", 1, "6-4", "64-48", 2, 8.0]]}, [["20110424", "ATL", "SFG", 0, 9, 6], ["20110423", "ATL", "SFG", 0, 5, 2], ["20110422", "ATL", "SFG", 0, 4, 1], ["20100808", "ATL", "SFG", 1, 6, 3], ["20100807", "ATL", "SFG", 1, 3, 0], ["20100806", "SFG", "ATL", 0, 3, 2], ["20100805", "ATL", "SFG", 1, 3, 2], ["20100411", "SFG", "ATL", 1, 6, 3], ["20100410", "ATL", "SFG", 0, 7, 2], ["20100409", "SFG", "ATL", 1, 5, 4]]], ["ATL201108170", {"Team name": "Giants", "Home": "35-25", "Road": "31-32", "ExtrInn": "10-7", "vsRHP": "46-46", "vsLHP": "20-11", "1-Run": "28-18", "vsEast": "12-19", "vsCntrl": "16-16", "vsWest": "28-17", "IL": "10-5", "last_10_game": [["0816", 0, "ATL", 0, "1-2", "66-57", 2, 3.5], ["0815", 0, "ATL", 0, "4-5", "66-56", 2, 2.5], ["0814", 0, "FLA", 1, "5-2", "66-55", 2, 2.0], ["0813", 0, "FLA", 1, "3-0", "65-55", 2, 2.0], ["0812", 0, "FLA", 0, "1-2", "64-55", 2, 2.0], ["0810", 1, "PIT", 0, "2-9", "64-54", 2, 0.5], ["0809", 1, "PIT", 1, "6-0", "64-53", 1, 0.5], ["0808", 1, "PIT", 0, "0-5", "63-53", 1, 0.5], ["0807", 1, "PHI", 1, "3-1", "63-52", 1, 0.5], ["0806", 1, "PHI", 0, "1-2", "62-52", 1, 0.5]]}, {"Team name": "Braves", "Home": "37-24", "Road": "35-27", "ExtrInn": "14-8", "vsRHP": "52-34", "vsLHP": "20-17", "1-Run": "23-18", "vsEast": "27-21", "vsCntrl": "19-13", "vsWest": "16-12", "IL": "10-5", "last_10_game": [["0816", 1, "SFG", 1, "2-1", "72-51", 2, 7.5], ["0815", 1, "SFG", 1, "5-4", "71-51", 2, 8.5], ["0814", 1, "CHC", 0, "5-6", "70-51", 2, 9.0], ["0813", 1, "CHC", 0, "4-8", "70-50", 2, 8.5], ["0812", 1, "CHC", 1, "10-4", "70-49", 2, 7.5], ["0810", 0, "FLA", 1, "6-2", "69-49", 2, 8.5], ["0809", 0, "FLA", 1, "4-3", "68-49", 2, 8.5], ["0808", 0, "FLA", 1, "8-5", "67-49", 2, 8.5], ["0807", 0, "NYM", 1, "6-5", "66-49", 2, 8.5], ["0806", 0, "NYM", 0, "7-11", "65-49", 2, 9.5]]}, [["20110816", "ATL", "SFG", 1, 2, 1], ["20110815", "ATL", "SFG", 1, 5, 4], ["20110424", "ATL", "SFG", 0, 9, 6], ["20110423", "ATL", "SFG", 0, 5, 2], ["20110422", "ATL", "SFG", 0, 4, 1], ["20100808", "ATL", "SFG", 1, 6, 3], ["20100807", "ATL", "SFG", 1, 3, 0], ["20100806", "SFG", "ATL", 0, 3, 2], ["20100805", "ATL", "SFG", 1, 3, 2], ["20100411", "SFG", "ATL", 1, 6, 3]]], ["ATL201108210", {"Team name": "D'backs", "Home": "36-26", "Road": "33-31", "ExtrInn": "6-4", "vsRHP": "51-39", "vsLHP": "18-18", "1-Run": "23-13", "vsEast": "15-12", "vsCntrl": "21-16", "vsWest": "23-21", "IL": "10-8", "last_10_game": [["0820", 0, "ATL", 0, "1-8", "69-57", 1, 2.5], ["0819", 0, "ATL", 0, "2-4", "69-56", 1, 2.5], ["0818", 0, "PHI", 0, "1-4", "69-55", 1, 2.5], ["0817", 0, "PHI", 0, "2-9", "69-54", 1, 2.5], ["0816", 0, "PHI", 1, "3-2", "69-53", 1, 3.5], ["0814", 1, "NYM", 1, "5-3", "68-53", 1, 2.0], ["0813", 1, "NYM", 1, "6-4", "67-53", 1, 2.0], ["0812", 1, "NYM", 1, "4-3", "66-53", 1, 2.0], ["0811", 1, "HOU", 1, "8-5", "65-53", 1, 1.0], ["0810", 1, "HOU", 1, "6-3", "64-53", 1, 0.5]]}, {"Team name": "Braves", "Home": "40-25", "Road": "35-27", "ExtrInn": "14-8", "vsRHP": "54-35", "vsLHP": "21-17", "1-Run": "24-18", "vsEast": "27-21", "vsCntrl": "19-13", "vsWest": "19-13", "IL": "10-5", "last_10_game": [["0820", 1, "ARI", 1, "8-1", "75-52", 2, 7.5], ["0819", 1, "ARI", 1, "4-2", "74-52", 2, 7.5], ["0818", 1, "SFG", 1, "1-0", "73-52", 2, 8.5], ["0817", 1, "SFG", 0, "5-7", "72-52", 2, 8.5], ["0816", 1, "SFG", 1, "2-1", "72-51", 2, 7.5], ["0815", 1, "SFG", 1, "5-4", "71-51", 2, 8.5], ["0814", 1, "CHC", 0, "5-6", "70-51", 2, 9.0], ["0813", 1, "CHC", 0, "4-8", "70-50", 2, 8.5], ["0812", 1, "CHC", 1, "10-4", "70-49", 2, 7.5], ["0810", 0, "FLA", 1, "6-2", "69-49", 2, 8.5]]}, [["20110820", "ATL", "ARI", 1, 8, 1], ["20110819", "ATL", "ARI", 1, 4, 2], ["20110519", "ARI", "ATL", 1, 2, 1], ["20110518", "ARI", "ATL", 1, 5, 4], ["20100610", "ATL", "ARI", 0, 11, 7], ["20100609", "ARI", "ATL", 1, 2, 1], ["20100608", "ATL", "ARI", 0, 7, 5], ["20100607", "ARI", "ATL", 1, 7, 4], ["20100516", "ATL", "ARI", 1, 13, 1], ["20100515", "ARI", "ATL", 0, 11, 1]]], ["ATL201108300", {"Team name": "Nationals", "Home": "37-28", "Road": "25-42", "ExtrInn": "10-7", "vsRHP": "46-55", "vsLHP": "16-15", "1-Run": "21-26", "vsEast": "21-28", "vsCntrl": "18-18", "vsWest": "15-17", "IL": "8-7", "last_10_game": [["0828", 0, "CIN", 0, "4-5", "62-70", 4, 22.5], ["0827", 0, "CIN", 0, "3-6", "62-69", 4, 22.0], ["0826", 0, "CIN", 0, "3-4", "62-68", 3, 21.5], ["0825", 1, "ARI", 0, "1-8", "62-67", 3, 21.5], ["0824", 1, "ARI", 0, "2-4", "62-66", 3, 21.0], ["0823", 1, "ARI", 0, "0-2", "62-65", 3, 21.0], ["0822", 1, "ARI", 1, "4-1", "62-64", 3, 20.0], ["0821", 1, "PHI", 1, "5-4", "61-64", 3, 20.0], ["0820", 1, "PHI", 0, "0-5", "60-64", 3, 21.0], ["0819", 1, "PHI", 1, "8-4", "60-63", 3, 20.0]]}, {"Team name": "Braves", "Home": "41-25", "Road": "38-29", "ExtrInn": "14-8", "vsRHP": "58-36", "vsLHP": "21-18", "1-Run": "26-19", "vsEast": "27-22", "vsCntrl": "22-14", "vsWest": "20-13", "IL": "10-5", "last_10_game": [["0826", 0, "NYM", 0, "0-6", "79-54", 2, 6.0], ["0825", 0, "CHC", 1, "8-3", "79-53", 2, 6.0], ["0824", 0, "CHC", 0, "2-3", "78-53", 2, 6.5], ["0823", 0, "CHC", 1, "5-4", "78-52", 2, 6.5], ["0822", 0, "CHC", 1, "3-0", "77-52", 2, 6.5], ["0821", 1, "ARI", 1, "1-0", "76-52", 2, 6.5], ["0820", 1, "ARI", 1, "8-1", "75-52", 2, 7.5], ["0819", 1, "ARI", 1, "4-2", "74-52", 2, 7.5], ["0818", 1, "SFG", 1, "1-0", "73-52", 2, 8.5], ["0817", 1, "SFG", 0, "5-7", "72-52", 2, 8.5]]}, [["20110803", "ATL", "WSN", 0, 6, 4], ["20110802", "WSN", "ATL", 1, 9, 3], ["20110801", "WSN", "ATL", 1, 5, 3], ["20110717", "ATL", "WSN", 1, 9, 8], ["20110716", "WSN", "ATL", 0, 5, 2], ["20110715", "ATL", "WSN", 1, 11, 1], ["20110512", "ATL", "WSN", 1, 6, 5], ["20110511", "WSN", "ATL", 0, 7, 3], ["20110510", "WSN", "ATL", 0, 7, 6], ["20110403", "ATL", "WSN", 0, 11, 2]]], ["ATL201108310", {"Team name": "Nationals", "Home": "37-28", "Road": "26-42", "ExtrInn": "10-7", "vsRHP": "47-55", "vsLHP": "16-15", "1-Run": "21-26", "vsEast": "22-28", "vsCntrl": "18-18", "vsWest": "15-17", "IL": "8-7", "last_10_game": [["0830", 0, "ATL", 1, "9-2", "63-70", 4, 23.0], ["0828", 0, "CIN", 0, "4-5", "62-70", 4, 22.5], ["0827", 0, "CIN", 0, "3-6", "62-69", 4, 22.0], ["0826", 0, "CIN", 0, "3-4", "62-68", 3, 21.5], ["0825", 1, "ARI", 0, "1-8", "62-67", 3, 21.5], ["0824", 1, "ARI", 0, "2-4", "62-66", 3, 21.0], ["0823", 1, "ARI", 0, "0-2", "62-65", 3, 21.0], ["0822", 1, "ARI", 1, "4-1", "62-64", 3, 20.0], ["0821", 1, "PHI", 1, "5-4", "61-64", 3, 20.0], ["0820", 1, "PHI", 0, "0-5", "60-64", 3, 21.0]]}, {"Team name": "Braves", "Home": "41-26", "Road": "38-29", "ExtrInn": "14-8", "vsRHP": "58-37", "vsLHP": "21-18", "1-Run": "26-19", "vsEast": "27-23", "vsCntrl": "22-14", "vsWest": "20-13", "IL": "10-5", "last_10_game": [["0830", 1, "WSN", 0, "2-9", "79-55", 2, 7.5], ["0826", 0, "NYM", 0, "0-6", "79-54", 2, 6.0], ["0825", 0, "CHC", 1, "8-3", "79-53", 2, 6.0], ["0824", 0, "CHC", 0, "2-3", "78-53", 2, 6.5], ["0823", 0, "CHC", 1, "5-4", "78-52", 2, 6.5], ["0822", 0, "CHC", 1, "3-0", "77-52", 2, 6.5], ["0821", 1, "ARI", 1, "1-0", "76-52", 2, 6.5], ["0820", 1, "ARI", 1, "8-1", "75-52", 2, 7.5], ["0819", 1, "ARI", 1, "4-2", "74-52", 2, 7.5], ["0818", 1, "SFG", 1, "1-0", "73-52", 2, 8.5]]}, [["20110830", "WSN", "ATL", 0, 9, 2], ["20110803", "ATL", "WSN", 0, 6, 4], ["20110802", "WSN", "ATL", 1, 9, 3], ["20110801", "WSN", "ATL", 1, 5, 3], ["20110717", "ATL", "WSN", 1, 9, 8], ["20110716", "WSN", "ATL", 0, 5, 2], ["20110715", "ATL", "WSN", 1, 11, 1], ["20110512", "ATL", "WSN", 1, 6, 5], ["20110511", "WSN", "ATL", 0, 7, 3], ["20110510", "WSN", "ATL", 0, 7, 6]]], ["ATL201109010", {"Team name": "Nationals", "Home": "37-28", "Road": "26-43", "ExtrInn": "10-7", "vsRHP": "47-56", "vsLHP": "16-15", "1-Run": "21-26", "vsEast": "22-29", "vsCntrl": "18-18", "vsWest": "15-17", "IL": "8-7", "last_10_game": [["0831", 0, "ATL", 0, "1-3", "63-71", 4, 24.0], ["0830", 0, "ATL", 1, "9-2", "63-70", 4, 23.0], ["0828", 0, "CIN", 0, "4-5", "62-70", 4, 22.5], ["0827", 0, "CIN", 0, "3-6", "62-69", 4, 22.0], ["0826", 0, "CIN", 0, "3-4", "62-68", 3, 21.5], ["0825", 1, "ARI", 0, "1-8", "62-67", 3, 21.5], ["0824", 1, "ARI", 0, "2-4", "62-66", 3, 21.0], ["0823", 1, "ARI", 0, "0-2", "62-65", 3, 21.0], ["0822", 1, "ARI", 1, "4-1", "62-64", 3, 20.0], ["0821", 1, "PHI", 1, "5-4", "61-64", 3, 20.0]]}, {"Team name": "Braves", "Home": "42-26", "Road": "38-29", "ExtrInn": "14-8", "vsRHP": "58-37", "vsLHP": "22-18", "1-Run": "26-19", "vsEast": "28-23", "vsCntrl": "22-14", "vsWest": "20-13", "IL": "10-5", "last_10_game": [["0831", 1, "WSN", 1, "3-1", "80-55", 2, 7.5], ["0830", 1, "WSN", 0, "2-9", "79-55", 2, 7.5], ["0826", 0, "NYM", 0, "0-6", "79-54", 2, 6.0], ["0825", 0, "CHC", 1, "8-3", "79-53", 2, 6.0], ["0824", 0, "CHC", 0, "2-3", "78-53", 2, 6.5], ["0823", 0, "CHC", 1, "5-4", "78-52", 2, 6.5], ["0822", 0, "CHC", 1, "3-0", "77-52", 2, 6.5], ["0821", 1, "ARI", 1, "1-0", "76-52", 2, 6.5], ["0820", 1, "ARI", 1, "8-1", "75-52", 2, 7.5], ["0819", 1, "ARI", 1, "4-2", "74-52", 2, 7.5]]}, [["20110831", "ATL", "WSN", 1, 3, 1], ["20110830", "WSN", "ATL", 0, 9, 2], ["20110803", "ATL", "WSN", 0, 6, 4], ["20110802", "WSN", "ATL", 1, 9, 3], ["20110801", "WSN", "ATL", 1, 5, 3], ["20110717", "ATL", "WSN", 1, 9, 8], ["20110716", "WSN", "ATL", 0, 5, 2], ["20110715", "ATL", "WSN", 1, 11, 1], ["20110512", "ATL", "WSN", 1, 6, 5], ["20110511", "WSN", "ATL", 0, 7, 3]]], ["ATL201109020", {"Team name": "Dodgers", "Home": "36-35", "Road": "30-35", "ExtrInn": "7-1", "vsRHP": "48-53", "vsLHP": "18-17", "1-Run": "19-18", "vsEast": "11-15", "vsCntrl": "19-19", "vsWest": "30-27", "IL": "6-9", "last_10_game": [["0901", 0, "PIT", 1, "6-4", "66-70", 3, 11.5], ["0831", 1, "SDP", 1, "4-2", "65-70", 3, 12.0], ["0830", 1, "SDP", 1, "8-5", "64-70", 3, 12.0], ["0829", 1, "SDP", 1, "4-1", "63-70", 3, 12.0], ["0828", 1, "COL", 0, "6-7", "62-70", 4, 12.0], ["0827", 1, "COL", 1, "7-6", "62-69", 3, 11.0], ["0826", 1, "COL", 1, "6-1", "61-69", 4, 11.0], ["0824", 0, "STL", 1, "9-4", "60-69", 4, 10.5], ["0823", 0, "STL", 1, "13-2", "59-69", 4, 10.5], ["0822", 0, "STL", 1, "2-1", "58-69", 4, 10.5]]}, {"Team name": "Braves", "Home": "43-26", "Road": "38-29", "ExtrInn": "14-8", "vsRHP": "59-37", "vsLHP": "22-18", "1-Run": "26-19", "vsEast": "29-23", "vsCntrl": "22-14", "vsWest": "20-13", "IL": "10-5", "last_10_game": [["0901", 1, "WSN", 1, "5-2", "81-55", 2, 7.5], ["0831", 1, "WSN", 1, "3-1", "80-55", 2, 7.5], ["0830", 1, "WSN", 0, "2-9", "79-55", 2, 7.5], ["0826", 0, "NYM", 0, "0-6", "79-54", 2, 6.0], ["0825", 0, "CHC", 1, "8-3", "79-53", 2, 6.0], ["0824", 0, "CHC", 0, "2-3", "78-53", 2, 6.5], ["0823", 0, "CHC", 1, "5-4", "78-52", 2, 6.5], ["0822", 0, "CHC", 1, "3-0", "77-52", 2, 6.5], ["0821", 1, "ARI", 1, "1-0", "76-52", 2, 6.5], ["0820", 1, "ARI", 1, "8-1", "75-52", 2, 7.5]]}, [["20110421", "LAD", "ATL", 1, 5, 3], ["20110420", "LAD", "ATL", 1, 6, 1], ["20110419", "ATL", "LAD", 0, 10, 1], ["20110418", "LAD", "ATL", 1, 4, 2], ["20100816", "ATL", "LAD", 1, 4, 3], ["20100815", "ATL", "LAD", 1, 13, 1], ["20100814", "LAD", "ATL", 0, 2, 1], ["20100813", "ATL", "LAD", 1, 1, 0], ["20100606", "LAD", "ATL", 1, 5, 4], ["20100605", "ATL", "LAD", 0, 9, 3]]], ["ATL201109120", {"Team name": "Marlins", "Home": "28-44", "Road": "38-35", "ExtrInn": "7-12", "vsRHP": "46-60", "vsLHP": "20-19", "1-Run": "24-30", "vsEast": "26-32", "vsCntrl": "20-17", "vsWest": "12-20", "IL": "8-10", "last_10_game": [["0911", 0, "PIT", 1, "4-1", "66-79", 5, 29.0], ["0910", 0, "PIT", 1, "3-0", "65-79", 5, 30.0], ["0909", 0, "PIT", 1, "13-4", "64-79", 5, 30.0], ["0907", 1, "NYM", 0, "0-1", "63-79", 5, 29.5], ["0906", 1, "NYM", 0, "4-7", "63-78", 5, 28.5], ["0905", 1, "NYM", 1, "9-3", "63-77", 5, 27.5], ["0904", 1, "PHI", 1, "5-4", "62-77", 5, 27.5], ["0903", 1, "PHI", 1, "8-4", "61-77", 5, 28.5], ["0902", 1, "PHI", 0, "3-5", "60-77", 5, 29.5], ["0901", 0, "NYM", 0, "5-7", "60-76", 5, 28.5]]}, {"Team name": "Braves", "Home": "44-28", "Road": "40-35", "ExtrInn": "14-10", "vsRHP": "61-43", "vsLHP": "23-20", "1-Run": "28-23", "vsEast": "31-26", "vsCntrl": "22-17", "vsWest": "21-15", "IL": "10-5", "last_10_game": [["0911", 0, "STL", 0, "3-6", "84-63", 2, 12.0], ["0910", 0, "STL", 0, "3-4", "84-62", 2, 12.0], ["0909", 0, "STL", 0, "3-4", "84-61", 2, 11.0], ["0908", 0, "NYM", 1, "5-1", "84-60", 2, 10.0], ["0908", 0, "NYM", 1, "6-5", "83-60", 2, 10.0], ["0907", 0, "PHI", 0, "2-3", "82-60", 2, 10.5], ["0906", 0, "PHI", 0, "3-6", "82-59", 2, 9.5], ["0905", 0, "PHI", 0, "0-9", "82-58", 2, 8.5], ["0904", 1, "LAD", 1, "4-3", "82-57", 2, 7.5], ["0903", 1, "LAD", 0, "1-2", "81-57", 2, 8.5]]}, [["20110810", "ATL", "FLA", 0, 6, 2], ["20110809", "ATL", "FLA", 0, 4, 3], ["20110808", "ATL", "FLA", 0, 8, 5], ["20110731", "FLA", "ATL", 0, 3, 1], ["20110730", "ATL", "FLA", 1, 5, 1], ["20110729", "ATL", "FLA", 1, 5, 0], ["20110609", "ATL", "FLA", 0, 3, 2], ["20110608", "ATL", "FLA", 0, 3, 2], ["20110607", "ATL", "FLA", 0, 1, 0], ["20110414", "FLA", "ATL", 0, 6, 5]]], ["ATL201109130", {"Team name": "Marlins", "Home": "28-44", "Road": "39-35", "ExtrInn": "8-12", "vsRHP": "47-60", "vsLHP": "20-19", "1-Run": "25-30", "vsEast": "27-32", "vsCntrl": "20-17", "vsWest": "12-20", "IL": "8-10", "last_10_game": [["0912", 0, "ATL", 1, "5-4", "67-79", 5, 28.0], ["0911", 0, "PIT", 1, "4-1", "66-79", 5, 29.0], ["0910", 0, "PIT", 1, "3-0", "65-79", 5, 30.0], ["0909", 0, "PIT", 1, "13-4", "64-79", 5, 30.0], ["0907", 1, "NYM", 0, "0-1", "63-79", 5, 29.5], ["0906", 1, "NYM", 0, "4-7", "63-78", 5, 28.5], ["0905", 1, "NYM", 1, "9-3", "63-77", 5, 27.5], ["0904", 1, "PHI", 1, "5-4", "62-77", 5, 27.5], ["0903", 1, "PHI", 1, "8-4", "61-77", 5, 28.5], ["0902", 1, "PHI", 0, "3-5", "60-77", 5, 29.5]]}, {"Team name": "Braves", "Home": "44-29", "Road": "40-35", "ExtrInn": "14-11", "vsRHP": "61-44", "vsLHP": "23-20", "1-Run": "28-24", "vsEast": "31-27", "vsCntrl": "22-17", "vsWest": "21-15", "IL": "10-5", "last_10_game": [["0912", 1, "FLA", 0, "4-5", "84-64", 2, 12.0], ["0911", 0, "STL", 0, "3-6", "84-63", 2, 12.0], ["0910", 0, "STL", 0, "3-4", "84-62", 2, 12.0], ["0909", 0, "STL", 0, "3-4", "84-61", 2, 11.0], ["0908", 0, "NYM", 1, "5-1", "84-60", 2, 10.0], ["0908", 0, "NYM", 1, "6-5", "83-60", 2, 10.0], ["0907", 0, "PHI", 0, "2-3", "82-60", 2, 10.5], ["0906", 0, "PHI", 0, "3-6", "82-59", 2, 9.5], ["0905", 0, "PHI", 0, "0-9", "82-58", 2, 8.5], ["0904", 1, "LAD", 1, "4-3", "82-57", 2, 7.5]]}, [["20110912", "FLA", "ATL", 0, 5, 4], ["20110810", "ATL", "FLA", 0, 6, 2], ["20110809", "ATL", "FLA", 0, 4, 3], ["20110808", "ATL", "FLA", 0, 8, 5], ["20110731", "FLA", "ATL", 0, 3, 1], ["20110730", "ATL", "FLA", 1, 5, 1], ["20110729", "ATL", "FLA", 1, 5, 0], ["20110609", "ATL", "FLA", 0, 3, 2], ["20110608", "ATL", "FLA", 0, 3, 2], ["20110607", "ATL", "FLA", 0, 1, 0]]], ["ATL201109160", {"Team name": "Mets", "Home": "31-44", "Road": "40-35", "ExtrInn": "7-6", "vsRHP": "54-58", "vsLHP": "17-21", "1-Run": "20-24", "vsEast": "29-37", "vsCntrl": "17-16", "vsWest": "16-17", "IL": "9-9", "last_10_game": [["0915", 1, "WSN", 0, "1-10", "71-79", 4, 27.0], ["0914", 1, "WSN", 0, "0-2", "71-78", 3, 25.5], ["0913", 1, "WSN", 0, "2-3", "71-77", 3, 24.5], ["0912", 1, "WSN", 0, "2-3", "71-76", 3, 24.5], ["0911", 1, "CHC", 0, "6-10", "71-75", 3, 24.5], ["0910", 1, "CHC", 0, "4-5", "71-74", 3, 24.5], ["0909", 1, "CHC", 1, "5-4", "71-73", 3, 23.5], ["0908", 1, "ATL", 0, "1-5", "70-73", 3, 23.5], ["0908", 1, "ATL", 0, "5-6", "70-72", 3, 23.5], ["0907", 0, "FLA", 1, "1-0", "70-71", 3, 22.0]]}, {"Team name": "Braves", "Home": "46-29", "Road": "40-35", "ExtrInn": "14-11", "vsRHP": "62-44", "vsLHP": "24-20", "1-Run": "28-24", "vsEast": "33-27", "vsCntrl": "22-17", "vsWest": "21-15", "IL": "10-5", "last_10_game": [["0914", 1, "FLA", 1, "4-1", "86-64", 2, 11.0], ["0913", 1, "FLA", 1, "7-1", "85-64", 2, 11.0], ["0912", 1, "FLA", 0, "4-5", "84-64", 2, 12.0], ["0911", 0, "STL", 0, "3-6", "84-63", 2, 12.0], ["0910", 0, "STL", 0, "3-4", "84-62", 2, 12.0], ["0909", 0, "STL", 0, "3-4", "84-61", 2, 11.0], ["0908", 0, "NYM", 1, "5-1", "84-60", 2, 10.0], ["0908", 0, "NYM", 1, "6-5", "83-60", 2, 10.0], ["0907", 0, "PHI", 0, "2-3", "82-60", 2, 10.5], ["0906", 0, "PHI", 0, "3-6", "82-59", 2, 9.5]]}, [["20110908", "ATL", "NYM", 0, 5, 1], ["20110908", "ATL", "NYM", 0, 6, 5], ["20110826", "NYM", "ATL", 1, 6, 0], ["20110807", "ATL", "NYM", 0, 6, 5], ["20110806", "NYM", "ATL", 1, 11, 7], ["20110805", "ATL", "NYM", 0, 4, 1], ["20110616", "ATL", "NYM", 1, 9, 8], ["20110615", "NYM", "ATL", 0, 4, 0], ["20110614", "NYM", "ATL", 0, 4, 3], ["20110605", "NYM", "ATL", 1, 6, 4]]], ["ATL201109170", {"Team name": "Mets", "Home": "31-44", "Road": "41-35", "ExtrInn": "7-6", "vsRHP": "55-58", "vsLHP": "17-21", "1-Run": "20-24", "vsEast": "30-37", "vsCntrl": "17-16", "vsWest": "16-17", "IL": "9-9", "last_10_game": [["0916", 0, "ATL", 1, "12-2", "72-79", 3, 26.0], ["0915", 1, "WSN", 0, "1-10", "71-79", 4, 27.0], ["0914", 1, "WSN", 0, "0-2", "71-78", 3, 25.5], ["0913", 1, "WSN", 0, "2-3", "71-77", 3, 24.5], ["0912", 1, "WSN", 0, "2-3", "71-76", 3, 24.5], ["0911", 1, "CHC", 0, "6-10", "71-75", 3, 24.5], ["0910", 1, "CHC", 0, "4-5", "71-74", 3, 24.5], ["0909", 1, "CHC", 1, "5-4", "71-73", 3, 23.5], ["0908", 1, "ATL", 0, "1-5", "70-73", 3, 23.5], ["0908", 1, "ATL", 0, "5-6", "70-72", 3, 23.5]]}, {"Team name": "Braves", "Home": "46-30", "Road": "40-35", "ExtrInn": "14-11", "vsRHP": "62-44", "vsLHP": "24-21", "1-Run": "28-24", "vsEast": "33-28", "vsCntrl": "22-17", "vsWest": "21-15", "IL": "10-5", "last_10_game": [["0916", 1, "NYM", 0, "2-12", "86-65", 2, 12.0], ["0914", 1, "FLA", 1, "4-1", "86-64", 2, 11.0], ["0913", 1, "FLA", 1, "7-1", "85-64", 2, 11.0], ["0912", 1, "FLA", 0, "4-5", "84-64", 2, 12.0], ["0911", 0, "STL", 0, "3-6", "84-63", 2, 12.0], ["0910", 0, "STL", 0, "3-4", "84-62", 2, 12.0], ["0909", 0, "STL", 0, "3-4", "84-61", 2, 11.0], ["0908", 0, "NYM", 1, "5-1", "84-60", 2, 10.0], ["0908", 0, "NYM", 1, "6-5", "83-60", 2, 10.0], ["0907", 0, "PHI", 0, "2-3", "82-60", 2, 10.5]]}, [["20110916", "NYM", "ATL", 0, 12, 2], ["20110908", "ATL", "NYM", 0, 5, 1], ["20110908", "ATL", "NYM", 0, 6, 5], ["20110826", "NYM", "ATL", 1, 6, 0], ["20110807", "ATL", "NYM", 0, 6, 5], ["20110806", "NYM", "ATL", 1, 11, 7], ["20110805", "ATL", "NYM", 0, 4, 1], ["20110616", "ATL", "NYM", 1, 9, 8], ["20110615", "NYM", "ATL", 0, 4, 0], ["20110614", "NYM", "ATL", 0, 4, 3]]], ["ATL201109270", {"Team name": "Phillies", "Home": "52-29", "Road": "48-31", "ExtrInn": "8-10", "vsRHP": "70-46", "vsLHP": "30-14", "1-Run": "27-19", "vsEast": "41-29", "vsCntrl": "27-16", "vsWest": "23-9", "IL": "9-6", "last_10_game": [["0926", 0, "ATL", 1, "4-2", "100-60", 1, 11.0], ["0925", 0, "NYM", 1, "9-4", "99-60", 1, 10.0], ["0924", 0, "NYM", 0, "3-6", "98-60", 1, 9.0], ["0924", 0, "NYM", 0, "1-2", "98-59", 1, 9.0], ["0922", 1, "WSN", 0, "1-6", "98-58", 1, 10.0], ["0921", 1, "WSN", 0, "5-7", "98-57", 1, 10.5], ["0920", 1, "WSN", 0, "0-3", "98-56", 1, 10.5], ["0920", 1, "WSN", 0, "3-4", "98-55", 1, 10.5], ["0919", 1, "STL", 0, "3-4", "98-54", 1, 12.0], ["0918", 1, "STL", 0, "0-5", "98-53", 1, 12.0]]}, {"Team name": "Braves", "Home": "47-32", "Road": "42-39", "ExtrInn": "14-11", "vsRHP": "65-48", "vsLHP": "24-23", "1-Run": "29-25", "vsEast": "36-34", "vsCntrl": "22-17", "vsWest": "21-15", "IL": "10-5", "last_10_game": [["0926", 1, "PHI", 0, "2-4", "89-71", 2, 11.0], ["0925", 0, "WSN", 0, "0-3", "89-70", 2, 10.0], ["0924", 0, "WSN", 0, "1-4", "89-69", 2, 9.0], ["0923", 0, "WSN", 1, "7-4", "89-68", 2, 9.5], ["0921", 0, "FLA", 0, "0-4", "88-68", 2, 10.5], ["0920", 0, "FLA", 1, "4-0", "88-67", 2, 10.5], ["0919", 0, "FLA", 0, "5-6", "87-67", 2, 12.0], ["0918", 1, "NYM", 0, "5-7", "87-66", 2, 12.0], ["0917", 1, "NYM", 1, "1-0", "87-65", 2, 12.0], ["0916", 1, "NYM", 0, "2-12", "86-65", 2, 12.0]]}, [["20110926", "PHI", "ATL", 0, 4, 2], ["20110907", "PHI", "ATL", 1, 3, 2], ["20110906", "PHI", "ATL", 1, 6, 3], ["20110905", "PHI", "ATL", 1, 9, 0], ["20110710", "PHI", "ATL", 1, 14, 1], ["20110709", "ATL", "PHI", 0, 4, 1], ["20110708", "PHI", "ATL", 1, 3, 2], ["20110515", "ATL", "PHI", 1, 3, 2], ["20110514", "ATL", "PHI", 1, 5, 3], ["20110513", "PHI", "ATL", 0, 5, 4]]], ["ATL201109280", {"Team name": "Phillies", "Home": "52-29", "Road": "49-31", "ExtrInn": "8-10", "vsRHP": "71-46", "vsLHP": "30-14", "1-Run": "27-19", "vsEast": "42-29", "vsCntrl": "27-16", "vsWest": "23-9", "IL": "9-6", "last_10_game": [["0927", 0, "ATL", 1, "7-1", "101-60", 1, 12.0], ["0926", 0, "ATL", 1, "4-2", "100-60", 1, 11.0], ["0925", 0, "NYM", 1, "9-4", "99-60", 1, 10.0], ["0924", 0, "NYM", 0, "3-6", "98-60", 1, 9.0], ["0924", 0, "NYM", 0, "1-2", "98-59", 1, 9.0], ["0922", 1, "WSN", 0, "1-6", "98-58", 1, 10.0], ["0921", 1, "WSN", 0, "5-7", "98-57", 1, 10.5], ["0920", 1, "WSN", 0, "0-3", "98-56", 1, 10.5], ["0920", 1, "WSN", 0, "3-4", "98-55", 1, 10.5], ["0919", 1, "STL", 0, "3-4", "98-54", 1, 12.0]]}, {"Team name": "Braves", "Home": "47-33", "Road": "42-39", "ExtrInn": "14-11", "vsRHP": "65-49", "vsLHP": "24-23", "1-Run": "29-25", "vsEast": "36-35", "vsCntrl": "22-17", "vsWest": "21-15", "IL": "10-5", "last_10_game": [["0927", 1, "PHI", 0, "1-7", "89-72", 2, 12.0], ["0926", 1, "PHI", 0, "2-4", "89-71", 2, 11.0], ["0925", 0, "WSN", 0, "0-3", "89-70", 2, 10.0], ["0924", 0, "WSN", 0, "1-4", "89-69", 2, 9.0], ["0923", 0, "WSN", 1, "7-4", "89-68", 2, 9.5], ["0921", 0, "FLA", 0, "0-4", "88-68", 2, 10.5], ["0920", 0, "FLA", 1, "4-0", "88-67", 2, 10.5], ["0919", 0, "FLA", 0, "5-6", "87-67", 2, 12.0], ["0918", 1, "NYM", 0, "5-7", "87-66", 2, 12.0], ["0917", 1, "NYM", 1, "1-0", "87-65", 2, 12.0]]}, [["20110927", "PHI", "ATL", 0, 7, 1], ["20110926", "PHI", "ATL", 0, 4, 2], ["20110907", "PHI", "ATL", 1, 3, 2], ["20110906", "PHI", "ATL", 1, 6, 3], ["20110905", "PHI", "ATL", 1, 9, 0], ["20110710", "PHI", "ATL", 1, 14, 1], ["20110709", "ATL", "PHI", 0, 4, 1], ["20110708", "PHI", "ATL", 1, 3, 2], ["20110515", "ATL", "PHI", 1, 3, 2], ["20110514", "ATL", "PHI", 1, 5, 3]]]]